语法练习/i2c/三态门/three_state.v
module three_state
(
    input   wire    data         ,
    input   wire    en_data      ,
    inout           IO_data      
);

wire       data_in  ;

assign IO_data = (en_data==1'b1) ? data : 1'bz ;
assign data_in = IO_data ;



endmodule

语法练习/i2c/三态门/tb_three_state.v
`include "three_state.v"

module tb_three_state;

wire tb_IO_data ;

reg [3:0] seed = 0;

reg     data1;
reg     data2;

reg     data1_en;
reg     data2_en;

//两个三态门 输出相互连接， 模仿 i2c接口 主机sda连接从机sda线
three_state  u1_three_state (
    .data                    ( data1       ),
    .en_data                 ( data1_en    ),

    .IO_data                 ( tb_IO_data    )
);


three_state  u2_three_state (
    .data                    ( data2       ),
    .en_data                 ( data2_en    ),

    .IO_data                 ( tb_IO_data    )
);

/*
输入 data_in，位宽【a-1:0】，即位宽a，其值范围2^a，Verilog语法即2**a； 2**a表示2的a次方。
所以如果需要模拟data_in的随机输入，通常这样调用：data_in = {$random}%(2**a);       

$random与$random()的用法、结果都是一致的
$random%b可以生成范围 [ ( -b+1 ) : (b- 1 ) ]内的随机数
{$random}%b可以生成范围 [ 0: (b- 1 ) ]内的随机数

$random 是Verilog提供的一个随机数生成系统任务，调用该任务后，将会返回一个32bit的integer类型的有符号的值。其调用格式有3种：
    $random;
    $random();
    $random(seed);

————————————————
版权声明：本文为CSDN博主「孤独的单刀」的原创文章，遵循CC 4.0 BY-SA版权协议，转载请附上原文出处链接及本声明。
原文链接：https://blog.csdn.net/wuzhikaidetb/article/details/126090626
*/

//初始化三态门状态
initial begin
    repeat (10) begin
        data1 ={$random}%(2); //
        data2 ={$random}%(2);
        data1_en = 0;
        data2_en = 0;
        #100;    
    end
    repeat (10)  
        begin
            data2 = {$random}%(2);
            data2 = {$random}%(2);
            data1_en = 0;
            data2_en = 1;
            #100;
        end
    repeat (10)  
        begin
            data2 = {$random}%(2);
            data2 = {$random}%(2);
            data1_en = 1;
            data2_en = 0;
            #100;
        end
    repeat (10)  
        begin
            data2 = {$random}%(2);
            data2 = {$random}%(2);
            data1_en = 1;
            data2_en = 1;
            #100;
        end
    $finish;
end

 
 

//仿真开始
initial begin
    forever begin
        #100;
        if ($time >= 2000000)  $finish ;
    end
end

initial begin
    $dumpfile("three_state.vcd");           //生成的vcd文件名称
    $dumpvars(0,u1_three_state,u2_three_state);    // tb模块名称 module 的名字
end






endmodule

语法练习/i2c/三态门/three_state.vcd
$date
	Tue Apr 18 20:31:10 2023
$end
$version
	Icarus Verilog
$end
$timescale
	1s
$end
$scope module tb_three_state $end
$scope module u1_three_state $end
$var wire 1 ! IO_data $end
$var wire 1 " data $end
$var wire 1 # data_in $end
$var wire 1 $ en_data $end
$upscope $end
$upscope $end
$scope module tb_three_state $end
$scope module u2_three_state $end
$var wire 1 ! IO_data $end
$var wire 1 % data $end
$var wire 1 & data_in $end
$var wire 1 ' en_data $end
$upscope $end
$upscope $end
$enddefinitions $end
$comment Show the parameter values. $end
$dumpall
$end
#0
$dumpvars
0'
z&
1%
0$
z#
0"
z!
$end
#100
1"
#300
0%
#400
1%
#500
0"
#600
0%
1"
#900
1%
#1000
1#
1&
1!
1'
1%
#1100
0#
0&
0!
0%
#1200
1#
1&
1!
1%
#1300
1%
#1500
0#
0&
0!
0%
#1700
1#
1&
1!
1%
#1800
1%
#2000
0'
1$
#2100
0%
#2200
1%
#2300
0%
#2600
0%
#2700
1%
#2800
0%
#3000
x#
x&
x!
1'
#3100
1#
1&
1!
1%
#3300
x#
x&
x!
0%
#3400
1#
1&
1!
1%
#3600
x#
x&
x!
0%
#3700
1#
1&
1!
1%
#3800
1%
#3900
x#
x&
x!
0%
