计数器/counter.v
module time_count(
    
        input wire clk,
        input wire rst_n,
        output reg flag
                  
                  );
    
    parameter MAX_count = 10; //计数器最
    
    reg [24:0] cnt ; //时钟分频计数器， 对系统时钟计
    
    always @(posedge clk or negedge rst_n) begin
        if (!rst_n) begin
            cnt  <= 24'b0;
            flag <= 1'b0;
        end
        else if (cnt < MAX_count - 1'b1)begin
            cnt  <= cnt + 1'b1;
            flag <= 1'b0;
        end
        else begin
            cnt  <= 24'b0;
            flag <= 1'b1;
        end
    end
    
endmodule

计数器/tb_counter.v

`include "counter.v"
//~ `New testbench
`timescale  1ms / 1ns

module tb_time_count;

// time_count Parameters
parameter PERIOD     = 100       ;
parameter MAX_count  = 2500;

// time_count Inputs
reg   clk_                                  = 1 ;
reg   rst_n_                               = 0 ;

// time_count Outputs
wire  flag_                                 ;


initial
begin
    forever #(PERIOD>>2)  clk_=~clk_;
end

initial
begin
    rst_n_  <=  1;
end

time_count u_time_count (
    .clk                     ( clk_     ),
    .rst_n                   ( rst_n_   ),
    .flag                    ( flag_    )
);


initial
begin
    forever begin
        #100;
        if ($time >= 2000000)  $finish ;
    end  
    $dumpfile("test.vcd");           //生成的vcd文件名称
    $dumpvars(0, tb_time_count);    // tb模块名称 module 的名字
end

endmodule

计数器/test.vcd
$date
	Wed Oct 12 11:04:54 2022
$end
$version
	Icarus Verilog
$end
$timescale
	1ns
$end
$scope module tb_time_count $end
$var wire 1 ! flag_ $end
$var parameter 32 " MAX_count $end
$var parameter 32 # PERIOD $end
$var reg 1 $ clk_ $end
$var reg 1 % rst_n_ $end
$scope module u_time_count $end
$var wire 1 $ clk $end
$var wire 1 % rst_n $end
$var parameter 32 & MAX_count $end
$var reg 25 ' cnt [24:0] $end
$var reg 1 ! flag $end
$upscope $end
$upscope $end
$enddefinitions $end
$comment Show the parameter values. $end
$dumpall
b1010 &
b1100100 #
b100111000100 "
$end
#0
$dumpvars
b0 '
1%
1$
0!
$end
#50000000
0$
#100000000
b1 '
1$
#150000000
0$
#200000000
b10 '
1$
#250000000
0$
#300000000
b11 '
1$
#350000000
0$
#400000000
b100 '
1$
#450000000
0$
#500000000
b101 '
1$
#550000000
0$
#600000000
b110 '
1$
#650000000
0$
#700000000
b111 '
1$
#750000000
0$
#800000000
b1000 '
1$
#850000000
0$
#900000000
b1001 '
1$
#950000000
0$
#1000000000
1!
b0 '
1$
#1050000000
0$
#1100000000
0!
b1 '
1$
#1150000000
0$
#1200000000
b10 '
1$
#1250000000
0$
#1300000000
b11 '
1$
#1350000000
0$
#1400000000
b100 '
1$
#1450000000
0$
#1500000000
b101 '
1$
#1550000000
0$
#1600000000
b110 '
1$
#1650000000
0$
#1700000000
b111 '
1$
#1750000000
0$
#1800000000
b1000 '
1$
#1850000000
0$
#1900000000
b1001 '
1$
#1950000000
0$
#2000000000
1!
b0 '
1$
#2050000000
0$
#2100000000
0!
b1 '
1$
#2150000000
0$
#2200000000
b10 '
1$
#2250000000
0$
#2300000000
b11 '
1$
#2350000000
0$
#2400000000
b100 '
1$
#2450000000
0$
#2500000000
b101 '
1$
#2550000000
0$
#2600000000
b110 '
1$
#2650000000
0$
#2700000000
b111 '
1$
#2750000000
0$
#2800000000
b1000 '
1$
#2850000000
0$
#2900000000
b1001 '
1$
#2950000000
0$
#3000000000
1!
b0 '
1$
#3050000000
0$
#3100000000
0!
b1 '
1$
#3150000000
0$
#3200000000
b10 '
1$
#3250000000
0$
#3300000000
b11 '
1$
#3350000000
0$
#3400000000
b100 '
1$
#3450000000
0$
#3500000000
b101 '
1$
#3550000000
0$
#3600000000
b110 '
1$
#3650000000
0$
#3700000000
b111 '
1$
#3750000000
0$
#3800000000
b1000 '
1$
#3850000000
0$
#3900000000
b1001 '
1$
#3950000000
0$
#4000000000
1!
b0 '
1$
#4050000000
0$
#4100000000
0!
b1 '
1$
#4150000000
0$
#4200000000
b10 '
1$
#4250000000
0$
#4300000000
b11 '
1$
#4350000000
0$
#4400000000
b100 '
1$
#4450000000
0$
#4500000000
b101 '
1$
#4550000000
0$
#4600000000
b110 '
1$
#4650000000
0$
#4700000000
b111 '
1$
#4750000000
0$
#4800000000
b1000 '
1$
#4850000000
0$
#4900000000
b1001 '
1$
#4950000000
0$
#5000000000
1!
b0 '
1$
#5050000000
0$
#5100000000
0!
b1 '
1$
#5150000000
0$
#5200000000
b10 '
1$
#5250000000
0$
#5300000000
b11 '
1$
#5350000000
0$
#5400000000
b100 '
1$
#5450000000
0$
#5500000000
b101 '
1$
#5550000000
0$
#5600000000
b110 '
1$
#5650000000
0$
#5700000000
b111 '
1$
#5750000000
0$
#5800000000
b1000 '
1$
#5850000000
0$
#5900000000
b1001 '
1$
#5950000000
0$
#6000000000
1!
b0 '
1$
#6050000000
0$
#6100000000
0!
b1 '
1$
#6150000000
0$
#6200000000
b10 '
1$
#6250000000
0$
#6300000000
b11 '
1$
#6350000000
0$
#6400000000
b100 '
1$
#6450000000
0$
#6500000000
b101 '
1$
#6550000000
0$
#6600000000
b110 '
1$
#6650000000
0$
#6700000000
b111 '
1$
#6750000000
0$
#6800000000
b1000 '
1$
#6850000000
0$
#6900000000
b1001 '
1$
#6950000000
0$
#7000000000
1!
b0 '
1$
#7050000000
0$
#7100000000
0!
b1 '
1$
#7150000000
0$
#7200000000
b10 '
1$
#7250000000
0$
#7300000000
b11 '
1$
#7350000000
0$
#7400000000
b100 '
1$
#7450000000
0$
#7500000000
b101 '
1$
#7550000000
0$
#7600000000
b110 '
1$
#7650000000
0$
#7700000000
b111 '
1$
#7750000000
0$
#7800000000
b1000 '
1$
#7850000000
0$
#7900000000
b1001 '
1$
#7950000000
0$
#8000000000
1!
b0 '
1$
#8050000000
0$
#8100000000
0!
b1 '
1$
#8150000000
0$
#8200000000
b10 '
1$
#8250000000
0$
#8300000000
b11 '
1$
#8350000000
0$
#8400000000
b100 '
1$
#8450000000
0$
#8500000000
b101 '
1$
#8550000000
0$
#8600000000
b110 '
1$
#8650000000
0$
#8700000000
b111 '
1$
#8750000000
0$
#8800000000
b1000 '
1$
#8850000000
0$
#8900000000
b1001 '
1$
#8950000000
0$
#9000000000
1!
b0 '
1$
#9050000000
0$
#9100000000
0!
b1 '
1$
#9150000000
0$
#9200000000
b10 '
1$
#9250000000
0$
#9300000000
b11 '
1$
#9350000000
0$
#9400000000
b100 '
1$
#9450000000
0$
#9500000000
b101 '
1$
#9550000000
0$
#9600000000
b110 '
1$
#9650000000
0$
#9700000000
b111 '
1$
#9750000000
0$
#9800000000
b1000 '
1$
#9850000000
0$
#9900000000
b1001 '
1$
#9950000000
0$
#10000000000
1!
b0 '
1$
#10050000000
0$
#10100000000
0!
b1 '
1$
#10150000000
0$
#10200000000
b10 '
1$
#10250000000
0$
#10300000000
b11 '
1$
#10350000000
0$
#10400000000
b100 '
1$
#10450000000
0$
#10500000000
b101 '
1$
#10550000000
0$
#10600000000
b110 '
1$
#10650000000
0$
#10700000000
b111 '
1$
#10750000000
0$
#10800000000
b1000 '
1$
#10850000000
0$
#10900000000
b1001 '
1$
#10950000000
0$
#11000000000
1!
b0 '
1$
#11050000000
0$
#11100000000
0!
b1 '
1$
#11150000000
0$
#11200000000
b10 '
1$
#11250000000
0$
#11300000000
b11 '
1$
#11350000000
0$
#11400000000
b100 '
1$
#11450000000
0$
#11500000000
b101 '
1$
#11550000000
0$
#11600000000
b110 '
1$
#11650000000
0$
#11700000000
b111 '
1$
#11750000000
0$
#11800000000
b1000 '
1$
#11850000000
0$
#11900000000
b1001 '
1$
#11950000000
0$
#12000000000
1!
b0 '
1$
#12050000000
0$
#12100000000
0!
b1 '
1$
#12150000000
0$
#12200000000
b10 '
1$
#12250000000
0$
#12300000000
b11 '
1$
#12350000000
0$
#12400000000
b100 '
1$
#12450000000
0$
#12500000000
b101 '
1$
#12550000000
0$
#12600000000
b110 '
1$
#12650000000
0$
#12700000000
b111 '
1$
#12750000000
0$
#12800000000
b1000 '
1$
#12850000000
0$
#12900000000
b1001 '
1$
#12950000000
0$
#13000000000
1!
b0 '
1$
#13050000000
0$
#13100000000
0!
b1 '
1$
#13150000000
0$
#13200000000
b10 '
1$
#13250000000
0$
#13300000000
b11 '
1$
#13350000000
0$
#13400000000
b100 '
1$
#13450000000
0$
#13500000000
b101 '
1$
#13550000000
0$
#13600000000
b110 '
1$
#13650000000
0$
#13700000000
b111 '
1$
#13750000000
0$
#13800000000
b1000 '
1$
#13850000000
0$
#13900000000
b1001 '
1$
#13950000000
0$
#14000000000
1!
b0 '
1$
#14050000000
0$
#14100000000
0!
b1 '
1$
#14150000000
0$
#14200000000
b10 '
1$
#14250000000
0$
#14300000000
b11 '
1$
#14350000000
0$
#14400000000
b100 '
1$
#14450000000
0$
#14500000000
b101 '
1$
#14550000000
0$
#14600000000
b110 '
1$
#14650000000
0$
#14700000000
b111 '
1$
#14750000000
0$
#14800000000
b1000 '
1$
#14850000000
0$
#14900000000
b1001 '
1$
#14950000000
0$
#15000000000
1!
b0 '
1$
#15050000000
0$
#15100000000
0!
b1 '
1$
#15150000000
0$
#15200000000
b10 '
1$
#15250000000
0$
#15300000000
b11 '
1$
#15350000000
0$
#15400000000
b100 '
1$
#15450000000
0$
#15500000000
b101 '
1$
#15550000000
0$
#15600000000
b110 '
1$
#15650000000
0$
#15700000000
b111 '
1$
#15750000000
0$
#15800000000
b1000 '
1$
#15850000000
0$
#15900000000
b1001 '
1$
#15950000000
0$
#16000000000
1!
b0 '
1$
#16050000000
0$
#16100000000
0!
b1 '
1$
#16150000000
0$
#16200000000
b10 '
1$
#16250000000
0$
#16300000000
b11 '
1$
#16350000000
0$
#16400000000
b100 '
1$
#16450000000
0$
#16500000000
b101 '
1$
#16550000000
0$
#16600000000
b110 '
1$
#16650000000
0$
#16700000000
b111 '
1$
#16750000000
0$
#16800000000
b1000 '
1$
#16850000000
0$
#16900000000
b1001 '
1$
#16950000000
0$
#17000000000
1!
b0 '
1$
#17050000000
0$
#17100000000
0!
b1 '
1$
#17150000000
0$
#17200000000
b10 '
1$
#17250000000
0$
#17300000000
b11 '
1$
#17350000000
0$
#17400000000
b100 '
1$
#17450000000
0$
#17500000000
b101 '
1$
#17550000000
0$
#17600000000
b110 '
1$
#17650000000
0$
#17700000000
b111 '
1$
#17750000000
0$
#17800000000
b1000 '
1$
#17850000000
0$
#17900000000
b1001 '
1$
#17950000000
0$
#18000000000
1!
b0 '
1$
#18050000000
0$
#18100000000
0!
b1 '
1$
#18150000000
0$
#18200000000
b10 '
1$
#18250000000
0$
#18300000000
b11 '
1$
#18350000000
0$
#18400000000
b100 '
1$
#18450000000
0$
#18500000000
b101 '
1$
#18550000000
0$
#18600000000
b110 '
1$
#18650000000
0$
#18700000000
b111 '
1$
#18750000000
0$
#18800000000
b1000 '
1$
#18850000000
0$
#18900000000
b1001 '
1$
#18950000000
0$
#19000000000
1!
b0 '
1$
#19050000000
0$
#19100000000
0!
b1 '
1$
#19150000000
0$
#19200000000
b10 '
1$
#19250000000
0$
#19300000000
b11 '
1$
#19350000000
0$
#19400000000
b100 '
1$
#19450000000
0$
#19500000000
b101 '
1$
#19550000000
0$
#19600000000
b110 '
1$
#19650000000
0$
#19700000000
b111 '
1$
#19750000000
0$
#19800000000
b1000 '
1$
#19850000000
0$
#19900000000
b1001 '
1$
#19950000000
0$
#20000000000
1!
b0 '
1$
#20050000000
0$
#20100000000
0!
b1 '
1$
#20150000000
0$
#20200000000
b10 '
1$
#20250000000
0$
#20300000000
b11 '
1$
#20350000000
0$
#20400000000
b100 '
1$
#20450000000
0$
#20500000000
b101 '
1$
#20550000000
0$
#20600000000
b110 '
1$
#20650000000
0$
#20700000000
b111 '
1$
#20750000000
0$
#20800000000
b1000 '
1$
#20850000000
0$
#20900000000
b1001 '
1$
#20950000000
0$
#21000000000
1!
b0 '
1$
#21050000000
0$
#21100000000
0!
b1 '
1$
#21150000000
0$
#21200000000
b10 '
1$
#21250000000
0$
#21300000000
b11 '
1$
#21350000000
0$
#21400000000
b100 '
1$
#21450000000
0$
#21500000000
b101 '
1$
#21550000000
0$
#21600000000
b110 '
1$
#21650000000
0$
#21700000000
b111 '
1$
#21750000000
0$
#21800000000
b1000 '
1$
#21850000000
0$
#21900000000
b1001 '
1$
#21950000000
0$
#22000000000
1!
b0 '
1$
#22050000000
0$
#22100000000
0!
b1 '
1$
#22150000000
0$
#22200000000
b10 '
1$
#22250000000
0$
#22300000000
b11 '
1$
#22350000000
0$
#22400000000
b100 '
1$
#22450000000
0$
#22500000000
b101 '
1$
#22550000000
0$
#22600000000
b110 '
1$
#22650000000
0$
#22700000000
b111 '
1$
#22750000000
0$
#22800000000
b1000 '
1$
#22850000000
0$
#22900000000
b1001 '
1$
#22950000000
0$
#23000000000
1!
b0 '
1$
#23050000000
0$
#23100000000
0!
b1 '
1$
#23150000000
0$
#23200000000
b10 '
1$
#23250000000
0$
#23300000000
b11 '
1$
#23350000000
0$
#23400000000
b100 '
1$
#23450000000
0$
#23500000000
b101 '
1$
#23550000000
0$
#23600000000
b110 '
1$
#23650000000
0$
#23700000000
b111 '
1$
#23750000000
0$
#23800000000
b1000 '
1$
#23850000000
0$
#23900000000
b1001 '
1$
#23950000000
0$
#24000000000
1!
b0 '
1$
#24050000000
0$
#24100000000
0!
b1 '
1$
#24150000000
0$
#24200000000
b10 '
1$
#24250000000
0$
#24300000000
b11 '
1$
#24350000000
0$
#24400000000
b100 '
1$
#24450000000
0$
#24500000000
b101 '
1$
#24550000000
0$
#24600000000
b110 '
1$
#24650000000
0$
#24700000000
b111 '
1$
#24750000000
0$
#24800000000
b1000 '
1$
#24850000000
0$
#24900000000
b1001 '
1$
#24950000000
0$
#25000000000
1!
b0 '
1$
#25050000000
0$
#25100000000
0!
b1 '
1$
#25150000000
0$
#25200000000
b10 '
1$
#25250000000
0$
#25300000000
b11 '
1$
#25350000000
0$
#25400000000
b100 '
1$
#25450000000
0$
#25500000000
b101 '
1$
#25550000000
0$
#25600000000
b110 '
1$
#25650000000
0$
#25700000000
b111 '
1$
#25750000000
0$
#25800000000
b1000 '
1$
#25850000000
0$
#25900000000
b1001 '
1$
#25950000000
0$
#26000000000
1!
b0 '
1$
#26050000000
0$
#26100000000
0!
b1 '
1$
#26150000000
0$
#26200000000
b10 '
1$
#26250000000
0$
#26300000000
b11 '
1$
#26350000000
0$
#26400000000
b100 '
1$
#26450000000
0$
#26500000000
b101 '
1$
#26550000000
0$
#26600000000
b110 '
1$
#26650000000
0$
#26700000000
b111 '
1$
#26750000000
0$
#26800000000
b1000 '
1$
#26850000000
0$
#26900000000
b1001 '
1$
#26950000000
0$
#27000000000
1!
b0 '
1$
#27050000000
0$
#27100000000
0!
b1 '
1$
#27150000000
0$
#27200000000
b10 '
1$
#27250000000
0$
#27300000000
b11 '
1$
#27350000000
0$
#27400000000
b100 '
1$
#27450000000
0$
#27500000000
b101 '
1$
#27550000000
0$
#27600000000
b110 '
1$
#27650000000
0$
#27700000000
b111 '
1$
#27750000000
0$
#27800000000
b1000 '
1$
#27850000000
0$
#27900000000
b1001 '
1$
#27950000000
0$
#28000000000
1!
b0 '
1$
#28050000000
0$
#28100000000
0!
b1 '
1$
#28150000000
0$
#28200000000
b10 '
1$
#28250000000
0$
#28300000000
b11 '
1$
#28350000000
0$
#28400000000
b100 '
1$
#28450000000
0$
#28500000000
b101 '
1$
#28550000000
0$
#28600000000
b110 '
1$
#28650000000
0$
#28700000000
b111 '
1$
#28750000000
0$
#28800000000
b1000 '
1$
#28850000000
0$
#28900000000
b1001 '
1$
#28950000000
0$
#29000000000
1!
b0 '
1$
#29050000000
0$
#29100000000
0!
b1 '
1$
#29150000000
0$
#29200000000
b10 '
1$
#29250000000
0$
#29300000000
b11 '
1$
#29350000000
0$
#29400000000
b100 '
1$
#29450000000
0$
#29500000000
b101 '
1$
#29550000000
0$
#29600000000
b110 '
1$
#29650000000
0$
#29700000000
b111 '
1$
#29750000000
0$
#29800000000
b1000 '
1$
#29850000000
0$
#29900000000
b1001 '
1$
#29950000000
0$
#30000000000
1!
b0 '
1$
#30050000000
0$
#30100000000
0!
b1 '
1$
#30150000000
0$
#30200000000
b10 '
1$
#30250000000
0$
#30300000000
b11 '
1$
#30350000000
0$
#30400000000
b100 '
1$
#30450000000
0$
#30500000000
b101 '
1$
#30550000000
0$
#30600000000
b110 '
1$
#30650000000
0$
#30700000000
b111 '
1$
#30750000000
0$
#30800000000
b1000 '
1$
#30850000000
0$
#30900000000
b1001 '
1$
#30950000000
0$
#31000000000
1!
b0 '
1$
#31050000000
0$
#31100000000
0!
b1 '
1$
#31150000000
0$
#31200000000
b10 '
1$
#31250000000
0$
#31300000000
b11 '
1$
#31350000000
0$
#31400000000
b100 '
1$
#31450000000
0$
#31500000000
b101 '
1$
#31550000000
0$
#31600000000
b110 '
1$
#31650000000
0$
#31700000000
b111 '
1$
#31750000000
0$
#31800000000
b1000 '
1$
#31850000000
0$
#31900000000
b1001 '
1$
#31950000000
0$
#32000000000
1!
b0 '
1$
#32050000000
0$
#32100000000
0!
b1 '
1$
#32150000000
0$
#32200000000
b10 '
1$
#32250000000
0$
#32300000000
b11 '
1$
#32350000000
0$
#32400000000
b100 '
1$
#32450000000
0$
#32500000000
b101 '
1$
#32550000000
0$
#32600000000
b110 '
1$
#32650000000
0$
#32700000000
b111 '
1$
#32750000000
0$
#32800000000
b1000 '
1$
#32850000000
0$
#32900000000
b1001 '
1$
#32950000000
0$
#33000000000
1!
b0 '
1$
#33050000000
0$
#33100000000
0!
b1 '
1$
#33150000000
0$
#33200000000
b10 '
1$
#33250000000
0$
#33300000000
b11 '
1$
#33350000000
0$
#33400000000
b100 '
1$
#33450000000
0$
#33500000000
b101 '
1$
#33550000000
0$
#33600000000
b110 '
1$
#33650000000
0$
#33700000000
b111 '
1$
#33750000000
0$
#33800000000
b1000 '
1$
#33850000000
0$
#33900000000
b1001 '
1$
#33950000000
0$
#34000000000
1!
b0 '
1$
#34050000000
0$
#34100000000
0!
b1 '
1$
#34150000000
0$
#34200000000
b10 '
1$
#34250000000
0$
#34300000000
b11 '
1$
#34350000000
0$
#34400000000
b100 '
1$
#34450000000
0$
#34500000000
b101 '
1$
#34550000000
0$
#34600000000
b110 '
1$
#34650000000
0$
#34700000000
b111 '
1$
#34750000000
0$
#34800000000
b1000 '
1$
#34850000000
0$
#34900000000
b1001 '
1$
#34950000000
0$
#35000000000
1!
b0 '
1$
#35050000000
0$
#35100000000
0!
b1 '
1$
#35150000000
0$
#35200000000
b10 '
1$
#35250000000
0$
#35300000000
b11 '
1$
#35350000000
0$
#35400000000
b100 '
1$
#35450000000
0$
#35500000000
b101 '
1$
#35550000000
0$
#35600000000
b110 '
1$
#35650000000
0$
#35700000000
b111 '
1$
#35750000000
0$
#35800000000
b1000 '
1$
#35850000000
0$
#35900000000
b1001 '
1$
#35950000000
0$
#36000000000
1!
b0 '
1$
#36050000000
0$
#36100000000
0!
b1 '
1$
#36150000000
0$
#36200000000
b10 '
1$
#36250000000
0$
#36300000000
b11 '
1$
#36350000000
0$
#36400000000
b100 '
1$
#36450000000
0$
#36500000000
b101 '
1$
#36550000000
0$
#36600000000
b110 '
1$
#36650000000
0$
#36700000000
b111 '
1$
#36750000000
0$
#36800000000
b1000 '
1$
#36850000000
0$
#36900000000
b1001 '
1$
#36950000000
0$
#37000000000
1!
b0 '
1$
#37050000000
0$
#37100000000
0!
b1 '
1$
#37150000000
0$
#37200000000
b10 '
1$
#37250000000
0$
#37300000000
b11 '
1$
#37350000000
0$
#37400000000
b100 '
1$
#37450000000
0$
#37500000000
b101 '
1$
#37550000000
0$
#37600000000
b110 '
1$
#37650000000
0$
#37700000000
b111 '
1$
#37750000000
0$
#37800000000
b1000 '
1$
#37850000000
0$
#37900000000
b1001 '
1$
#37950000000
0$
#38000000000
1!
b0 '
1$
#38050000000
0$
#38100000000
0!
b1 '
1$
#38150000000
0$
#38200000000
b10 '
1$
#38250000000
0$
#38300000000
b11 '
1$
#38350000000
0$
#38400000000
b100 '
1$
#38450000000
0$
#38500000000
b101 '
1$
#38550000000
0$
#38600000000
b110 '
1$
#38650000000
0$
#38700000000
b111 '
1$
#38750000000
0$
#38800000000
b1000 '
1$
#38850000000
0$
#38900000000
b1001 '
1$
#38950000000
0$
#39000000000
1!
b0 '
1$
#39050000000
0$
#39100000000
0!
b1 '
1$
#39150000000
0$
#39200000000
b10 '
1$
#39250000000
0$
#39300000000
b11 '
1$
#39350000000
0$
#39400000000
b100 '
1$
#39450000000
0$
#39500000000
b101 '
1$
#39550000000
0$
#39600000000
b110 '
1$
#39650000000
0$
#39700000000
b111 '
1$
#39750000000
0$
#39800000000
b1000 '
1$
#39850000000
0$
#39900000000
b1001 '
1$
#39950000000
0$
#40000000000
1!
b0 '
1$
#40050000000
0$
#40100000000
0!
b1 '
1$
#40150000000
0$
#40200000000
b10 '
1$
#40250000000
0$
#40300000000
b11 '
1$
#40350000000
0$
#40400000000
b100 '
1$
#40450000000
0$
#40500000000
b101 '
1$
#40550000000
0$
#40600000000
b110 '
1$
#40650000000
0$
#40700000000
b111 '
1$
#40750000000
0$
#40800000000
b1000 '
1$
#40850000000
0$
#40900000000
b1001 '
1$
#40950000000
0$
#41000000000
1!
b0 '
1$
#41050000000
0$
#41100000000
0!
b1 '
1$
#41150000000
0$
#41200000000
b10 '
1$
#41250000000
0$
#41300000000
b11 '
1$
#41350000000
0$
#41400000000
b100 '
1$
#41450000000
0$
#41500000000
b101 '
1$
#41550000000
0$
#41600000000
b110 '
1$
#41650000000
0$
#41700000000
b111 '
1$
#41750000000
0$
#41800000000
b1000 '
1$
#41850000000
0$
#41900000000
b1001 '
1$
#41950000000
0$
#42000000000
1!
b0 '
1$
#42050000000
0$
#42100000000
0!
b1 '
1$
#42150000000
0$
#42200000000
b10 '
1$
#42250000000
0$
#42300000000
b11 '
1$
#42350000000
0$
#42400000000
b100 '
1$
#42450000000
0$
#42500000000
b101 '
1$
#42550000000
0$
#42600000000
b110 '
1$
#42650000000
0$
#42700000000
b111 '
1$
#42750000000
0$
#42800000000
b1000 '
1$
#42850000000
0$
#42900000000
b1001 '
1$
#42950000000
0$
#43000000000
1!
b0 '
1$
#43050000000
0$
#43100000000
0!
b1 '
1$
#43150000000
0$
#43200000000
b10 '
1$
#43250000000
0$
#43300000000
b11 '
1$
#43350000000
0$
#43400000000
b100 '
1$
#43450000000
0$
#43500000000
b101 '
1$
#43550000000
0$
#43600000000
b110 '
1$
#43650000000
0$
#43700000000
b111 '
1$
#43750000000
0$
#43800000000
b1000 '
1$
#43850000000
0$
#43900000000
b1001 '
1$
#43950000000
0$
#44000000000
1!
b0 '
1$
#44050000000
0$
#44100000000
0!
b1 '
1$
#44150000000
0$
#44200000000
b10 '
1$
#44250000000
0$
#44300000000
b11 '
1$
#44350000000
0$
#44400000000
b100 '
1$
#44450000000
0$
#44500000000
b101 '
1$
#44550000000
0$
#44600000000
b110 '
1$
#44650000000
0$
#44700000000
b111 '
1$
#44750000000
0$
#44800000000
b1000 '
1$
#44850000000
0$
#44900000000
b1001 '
1$
#44950000000
0$
#45000000000
1!
b0 '
1$
#45050000000
0$
#45100000000
0!
b1 '
1$
#45150000000
0$
#45200000000
b10 '
1$
#45250000000
0$
#45300000000
b11 '
1$
#45350000000
0$
#45400000000
b100 '
1$
#45450000000
0$
#45500000000
b101 '
1$
#45550000000
0$
#45600000000
b110 '
1$
#45650000000
0$
#45700000000
b111 '
1$
#45750000000
0$
#45800000000
b1000 '
1$
#45850000000
0$
#45900000000
b1001 '
1$
#45950000000
0$
#46000000000
1!
b0 '
1$
#46050000000
0$
#46100000000
0!
b1 '
1$
#46150000000
0$
#46200000000
b10 '
1$
#46250000000
0$
#46300000000
b11 '
1$
#46350000000
0$
#46400000000
b100 '
1$
#46450000000
0$
#46500000000
b101 '
1$
#46550000000
0$
#46600000000
b110 '
1$
#46650000000
0$
#46700000000
b111 '
1$
#46750000000
0$
#46800000000
b1000 '
1$
#46850000000
0$
#46900000000
b1001 '
1$
#46950000000
0$
#47000000000
1!
b0 '
1$
#47050000000
0$
#47100000000
0!
b1 '
1$
#47150000000
0$
#47200000000
b10 '
1$
#47250000000
0$
#47300000000
b11 '
1$
#47350000000
0$
#47400000000
b100 '
1$
#47450000000
0$
#47500000000
b101 '
1$
#47550000000
0$
#47600000000
b110 '
1$
#47650000000
0$
#47700000000
b111 '
1$
#47750000000
0$
#47800000000
b1000 '
1$
#47850000000
0$
#47900000000
b1001 '
1$
#47950000000
0$
#48000000000
1!
b0 '
1$
#48050000000
0$
#48100000000
0!
b1 '
1$
#48150000000
0$
#48200000000
b10 '
1$
#48250000000
0$
#48300000000
b11 '
1$
#48350000000
0$
#48400000000
b100 '
1$
#48450000000
0$
#48500000000
b101 '
1$
#48550000000
0$
#48600000000
b110 '
1$
#48650000000
0$
#48700000000
b111 '
1$
#48750000000
0$
#48800000000
b1000 '
1$
#48850000000
0$
#48900000000
b1001 '
1$
#48950000000
0$
#49000000000
1!
b0 '
1$
#49050000000
0$
#49100000000
0!
b1 '
1$
#49150000000
0$
#49200000000
b10 '
1$
#49250000000
0$
#49300000000
b11 '
1$
#49350000000
0$
#49400000000
b100 '
1$
#49450000000
0$
#49500000000
b101 '
1$
#49550000000
0$
#49600000000
b110 '
1$
#49650000000
0$
#49700000000
b111 '
1$
#49750000000
0$
#49800000000
b1000 '
1$
#49850000000
0$
#49900000000
b1001 '
1$
#49950000000
0$
#50000000000
1!
b0 '
1$
#50050000000
0$
#50100000000
0!
b1 '
1$
#50150000000
0$
#50200000000
b10 '
1$
#50250000000
0$
#50300000000
b11 '
1$
#50350000000
0$
#50400000000
b100 '
1$
#50450000000
0$
#50500000000
b101 '
1$
#50550000000
0$
#50600000000
b110 '
1$
#50650000000
0$
#50700000000
b111 '
1$
#50750000000
0$
#50800000000
b1000 '
1$
#50850000000
0$
#50900000000
b1001 '
1$
#50950000000
0$
#51000000000
1!
b0 '
1$
#51050000000
0$
#51100000000
0!
b1 '
1$
#51150000000
0$
#51200000000
b10 '
1$
#51250000000
0$
#51300000000
b11 '
1$
#51350000000
0$
#51400000000
b100 '
1$
#51450000000
0$
#51500000000
b101 '
1$
#51550000000
0$
#51600000000
b110 '
1$
#51650000000
0$
#51700000000
b111 '
1$
#51750000000
0$
#51800000000
b1000 '
1$
#51850000000
0$
#51900000000
b1001 '
1$
#51950000000
0$
#52000000000
1!
b0 '
1$
#52050000000
0$
#52100000000
0!
b1 '
1$
#52150000000
0$
#52200000000
b10 '
1$
#52250000000
0$
#52300000000
b11 '
1$
#52350000000
0$
#52400000000
b100 '
1$
#52450000000
0$
#52500000000
b101 '
1$
#52550000000
0$
#52600000000
b110 '
1$
#52650000000
0$
#52700000000
b111 '
1$
#52750000000
0$
#52800000000
b1000 '
1$
#52850000000
0$
#52900000000
b1001 '
1$
#52950000000
0$
#53000000000
1!
b0 '
1$
#53050000000
0$
#53100000000
0!
b1 '
1$
#53150000000
0$
#53200000000
b10 '
1$
#53250000000
0$
#53300000000
b11 '
1$
#53350000000
0$
#53400000000
b100 '
1$
#53450000000
0$
#53500000000
b101 '
1$
#53550000000
0$
#53600000000
b110 '
1$
#53650000000
0$
#53700000000
b111 '
1$
#53750000000
0$
#53800000000
b1000 '
1$
#53850000000
0$
#53900000000
b1001 '
1$
#53950000000
0$
#54000000000
1!
b0 '
1$
#54050000000
0$
#54100000000
0!
b1 '
1$
#54150000000
0$
#54200000000
b10 '
1$
#54250000000
0$
#54300000000
b11 '
1$
#54350000000
0$
#54400000000
b100 '
1$
#54450000000
0$
#54500000000
b101 '
1$
#54550000000
0$
#54600000000
b110 '
1$
#54650000000
0$
#54700000000
b111 '
1$
#54750000000
0$
#54800000000
b1000 '
1$
#54850000000
0$
#54900000000
b1001 '
1$
#54950000000
0$
#55000000000
1!
b0 '
1$
#55050000000
0$
#55100000000
0!
b1 '
1$
#55150000000
0$
#55200000000
b10 '
1$
#55250000000
0$
#55300000000
b11 '
1$
#55350000000
0$
#55400000000
b100 '
1$
#55450000000
0$
#55500000000
b101 '
1$
#55550000000
0$
#55600000000
b110 '
1$
#55650000000
0$
#55700000000
b111 '
1$
#55750000000
0$
#55800000000
b1000 '
1$
#55850000000
0$
#55900000000
b1001 '
1$
#55950000000
0$
#56000000000
1!
b0 '
1$
#56050000000
0$
#56100000000
0!
b1 '
1$
#56150000000
0$
#56200000000
b10 '
1$
#56250000000
0$
#56300000000
b11 '
1$
#56350000000
0$
#56400000000
b100 '
1$
#56450000000
0$
#56500000000
b101 '
1$
#56550000000
0$
#56600000000
b110 '
1$
#56650000000
0$
#56700000000
b111 '
1$
#56750000000
0$
#56800000000
b1000 '
1$
#56850000000
0$
#56900000000
b1001 '
1$
#56950000000
0$
#57000000000
1!
b0 '
1$
#57050000000
0$
#57100000000
0!
b1 '
1$
#57150000000
0$
#57200000000
b10 '
1$
#57250000000
0$
#57300000000
b11 '
1$
#57350000000
0$
#57400000000
b100 '
1$
#57450000000
0$
#57500000000
b101 '
1$
#57550000000
0$
#57600000000
b110 '
1$
#57650000000
0$
#57700000000
b111 '
1$
#57750000000
0$
#57800000000
b1000 '
1$
#57850000000
0$
#57900000000
b1001 '
1$
#57950000000
0$
#58000000000
1!
b0 '
1$
#58050000000
0$
#58100000000
0!
b1 '
1$
#58150000000
0$
#58200000000
b10 '
1$
#58250000000
0$
#58300000000
b11 '
1$
#58350000000
0$
#58400000000
b100 '
1$
#58450000000
0$
#58500000000
b101 '
1$
#58550000000
0$
#58600000000
b110 '
1$
#58650000000
0$
#58700000000
b111 '
1$
#58750000000
0$
#58800000000
b1000 '
1$
#58850000000
0$
#58900000000
b1001 '
1$
#58950000000
0$
