呼吸灯pwm/breath_led.v
`timescale  1ns/1ns
////////////////////////////////////////////////////////////////////////
// Author        : EmbedFire
// Create Date   : 2019/07/10
// Module Name   : breath_led
// Project Name  : breath_led
// Target Devices: Altera EP4CE10F17C8N
// Tool Versions : Quartus 13.0
// Description   : 呼吸灯
//
// Revision      : V1.0
// Additional Comments:
// 
// 实验平台: 野火_征途Pro_FPGA开发板
// 公司    : http://www.embedfire.com
// 论坛    : http://www.firebbs.cn
// 淘宝    : https://fire-stm32.taobao.com
////////////////////////////////////////////////////////////////////////

module  breath_led
#(
    parameter CNT_1US_MAX = 6'd49   ,
    parameter CNT_1MS_MAX = 10'd999 ,
    parameter CNT_1S_MAX  = 10'd999
)
(
    input   wire    sys_clk     ,   //系统时钟50Mhz
    input   wire    sys_rst_n   ,   //全局复位

    output  reg     led_out         //输出信号，控制led灯
);

//********************************************************************//
//****************** Parameter and Internal Signal *******************//
//********************************************************************//
//reg define
reg [5:0]   cnt_1us     ;
reg [9:0]   cnt_1ms     ;
reg [9:0]   cnt_1s      ;
reg         cnt_1s_en   ;

//********************************************************************/
//***************************** Main Code ****************************//
//********************************************************************//

//cnt_1us:1us计数器
always@(posedge sys_clk or negedge sys_rst_n)
    if(sys_rst_n == 1'b0)
        cnt_1us <= 6'b0;
    else    if(cnt_1us == CNT_1US_MAX)
        cnt_1us <= 6'b0;
    else
        cnt_1us <= cnt_1us + 1'b1; //每次累加 1ns 累加够1000次为1us

//cnt_1ms:1ms计数器
always@(posedge sys_clk or negedge sys_rst_n)
    if(sys_rst_n == 1'b0)
        cnt_1ms <= 10'b0;
    else    if(cnt_1ms == CNT_1MS_MAX && cnt_1us == CNT_1US_MAX)
        cnt_1ms <= 10'b0;
    else    if(cnt_1us == CNT_1US_MAX)
        cnt_1ms <= cnt_1ms + 1'b1; //每次累加 1us 累加够1000次为1ms

//cnt_1s:1s计数器
always@(posedge sys_clk or negedge sys_rst_n)
    if(sys_rst_n == 1'b0)
        cnt_1s <= 10'b0;
    else    if(cnt_1s == CNT_1S_MAX && cnt_1ms == CNT_1MS_MAX 
                                        && cnt_1us == CNT_1US_MAX)
        cnt_1s <= 10'b0;
    else    if(cnt_1ms == CNT_1MS_MAX && cnt_1us == CNT_1US_MAX)
        cnt_1s <= cnt_1s + 1'b1;  //每次累加 1ms 累加够1000次为1s

//cnt_1s_en:1s计数器使能信号
always@(posedge sys_clk or negedge sys_rst_n)
    if(sys_rst_n == 1'b0)
        cnt_1s_en <= 1'b0;
    else    if(cnt_1s == CNT_1S_MAX && cnt_1ms == CNT_1MS_MAX 
                                            && cnt_1us == CNT_1US_MAX)
        cnt_1s_en <= ~cnt_1s_en;

//led_out:输出信号连接到外部的led灯
always@(posedge sys_clk or negedge sys_rst_n)
    if(sys_rst_n == 1'b0)
        led_out <= 1'b0;  //在这 1秒内， 占空比为 cnt_1ms/cnt_1s;在这 1秒内， 占空比为 1- (cnt_1ms/cnt_1s)
    else    if( (cnt_1s_en == 1'b1 && cnt_1ms < cnt_1s) ||    // 渐渐亮起   pwm占空比
                (cnt_1s_en == 1'b0 && cnt_1ms > cnt_1s)   )   // 渐渐熄灭   pwm占空比
        led_out <= 1'b0;
    else
        led_out <= 1'b1;
endmodule

呼吸灯pwm/tb_breath_led.v
`timescale  1ns/1ns
`include "breath_led.v"
////////////////////////////////////////////////////////////////////////
// Author        : EmbedFire
// Create Date   : 2019/07/10
// Module Name   : tb_breath_led
// Project Name  : breath_led
// Target Devices: Altera EP4CE10F17C8N
// Tool Versions : Quartus 13.0
// Description   : 呼吸灯仿真文件
//
// Revision      : V1.0
// Additional Comments:
// 
// 实验平台: 野火_征途Pro_FPGA开发板
// 公司    : http://www.embedfire.com
// 论坛    : http://www.firebbs.cn
// 淘宝    : https://fire-stm32.taobao.com
////////////////////////////////////////////////////////////////////////

module  tb_breath_led();

//********************************************************************//
//****************** Parameter and Internal Signal *******************//
//********************************************************************//
//wire  define
wire    led_out     ;

//reg   define
reg     sys_clk     ;
reg     sys_rst_n   ;

//********************************************************************/
//***************************** Main Code ****************************//
//********************************************************************//
//初始化系统时钟、全局复位
initial begin
    sys_clk    = 1'b1;
    sys_rst_n <= 1'b0;
    #20
    sys_rst_n <= 1'b1;
end

//sys_clk:模拟系统时钟，每10ns电平翻转一次，周期为20ns，频率为50Mhz
always #10 sys_clk = ~sys_clk;

//********************************************************************//
//*************************** Instantiation **************************//
//********************************************************************//
//-------------------- breath_led_inst --------------------
breath_led
#(
    .CNT_1US_MAX(6'd4   ),
    .CNT_1MS_MAX(10'd9  ),
    .CNT_1S_MAX (10'd9  )
)
breath_led_inst
(
    .sys_clk    (sys_clk    ),  //input     sys_clk
    .sys_rst_n  (sys_rst_n  ),  //input     sys_rst_n

    .led_out    (led_out    )   //output    led_out
);

initial
begin
    forever begin
        #100;
        if ($time >= 2000000)  $finish ;
    end  
end
initial
begin
    $dumpfile("test.vcd");           //生成的vcd文件名称
    $dumpvars(0, tb_breath_led);    // tb模块名称 module 的名字
end

endmodule

呼吸灯pwm/test.vcd
$date
	Sat Nov 12 21:53:52 2022
$end
$version
	Icarus Verilog
$end
$timescale
	1ns
$end
$scope module tb_breath_led $end
$var wire 1 ! led_out $end
$var reg 1 " sys_clk $end
$var reg 1 # sys_rst_n $end
$scope module breath_led_inst $end
$var wire 1 " sys_clk $end
$var wire 1 # sys_rst_n $end
$var parameter 10 $ CNT_1MS_MAX $end
$var parameter 10 % CNT_1S_MAX $end
$var parameter 6 & CNT_1US_MAX $end
$var reg 10 ' cnt_1ms [9:0] $end
$var reg 10 ( cnt_1s [9:0] $end
$var reg 1 ) cnt_1s_en $end
$var reg 6 * cnt_1us [5:0] $end
$var reg 1 ! led_out $end
$upscope $end
$upscope $end
$enddefinitions $end
$comment Show the parameter values. $end
$dumpall
b100 &
b1001 %
b1001 $
$end
#0
$dumpvars
b0 *
0)
b0 (
b0 '
0#
1"
0!
$end
#10
0"
#20
1#
1"
#30
0"
#40
1!
b1 *
1"
#50
0"
#60
b10 *
1"
#70
0"
#80
b11 *
1"
#90
0"
#100
b100 *
1"
#110
0"
#120
b1 '
b0 *
1"
#130
0"
#140
b1 *
0!
1"
#150
0"
#160
b10 *
1"
#170
0"
#180
b11 *
1"
#190
0"
#200
b100 *
1"
#210
0"
#220
b0 *
b10 '
1"
#230
0"
#240
b1 *
1"
#250
0"
#260
b10 *
1"
#270
0"
#280
b11 *
1"
#290
0"
#300
b100 *
1"
#310
0"
#320
b11 '
b0 *
1"
#330
0"
#340
b1 *
1"
#350
0"
#360
b10 *
1"
#370
0"
#380
b11 *
1"
#390
0"
#400
b100 *
1"
#410
0"
#420
b0 *
b100 '
1"
#430
0"
#440
b1 *
1"
#450
0"
#460
b10 *
1"
#470
0"
#480
b11 *
1"
#490
0"
#500
b100 *
1"
#510
0"
#520
b101 '
b0 *
1"
#530
0"
#540
b1 *
1"
#550
0"
#560
b10 *
1"
#570
0"
#580
b11 *
1"
#590
0"
#600
b100 *
1"
#610
0"
#620
b0 *
b110 '
1"
#630
0"
#640
b1 *
1"
#650
0"
#660
b10 *
1"
#670
0"
#680
b11 *
1"
#690
0"
#700
b100 *
1"
#710
0"
#720
b111 '
b0 *
1"
#730
0"
#740
b1 *
1"
#750
0"
#760
b10 *
1"
#770
0"
#780
b11 *
1"
#790
0"
#800
b100 *
1"
#810
0"
#820
b0 *
b1000 '
1"
#830
0"
#840
b1 *
1"
#850
0"
#860
b10 *
1"
#870
0"
#880
b11 *
1"
#890
0"
#900
b100 *
1"
#910
0"
#920
b1001 '
b0 *
1"
#930
0"
#940
b1 *
1"
#950
0"
#960
b10 *
1"
#970
0"
#980
b11 *
1"
#990
0"
#1000
b100 *
1"
#1010
0"
#1020
b0 *
b0 '
b1 (
1"
#1030
0"
#1040
1!
b1 *
1"
#1050
0"
#1060
b10 *
1"
#1070
0"
#1080
b11 *
1"
#1090
0"
#1100
b100 *
1"
#1110
0"
#1120
b1 '
b0 *
1"
#1130
0"
#1140
b1 *
1"
#1150
0"
#1160
b10 *
1"
#1170
0"
#1180
b11 *
1"
#1190
0"
#1200
b100 *
1"
#1210
0"
#1220
b0 *
b10 '
1"
#1230
0"
#1240
0!
b1 *
1"
#1250
0"
#1260
b10 *
1"
#1270
0"
#1280
b11 *
1"
#1290
0"
#1300
b100 *
1"
#1310
0"
#1320
b11 '
b0 *
1"
#1330
0"
#1340
b1 *
1"
#1350
0"
#1360
b10 *
1"
#1370
0"
#1380
b11 *
1"
#1390
0"
#1400
b100 *
1"
#1410
0"
#1420
b0 *
b100 '
1"
#1430
0"
#1440
b1 *
1"
#1450
0"
#1460
b10 *
1"
#1470
0"
#1480
b11 *
1"
#1490
0"
#1500
b100 *
1"
#1510
0"
#1520
b101 '
b0 *
1"
#1530
0"
#1540
b1 *
1"
#1550
0"
#1560
b10 *
1"
#1570
0"
#1580
b11 *
1"
#1590
0"
#1600
b100 *
1"
#1610
0"
#1620
b0 *
b110 '
1"
#1630
0"
#1640
b1 *
1"
#1650
0"
#1660
b10 *
1"
#1670
0"
#1680
b11 *
1"
#1690
0"
#1700
b100 *
1"
#1710
0"
#1720
b111 '
b0 *
1"
#1730
0"
#1740
b1 *
1"
#1750
0"
#1760
b10 *
1"
#1770
0"
#1780
b11 *
1"
#1790
0"
#1800
b100 *
1"
#1810
0"
#1820
b0 *
b1000 '
1"
#1830
0"
#1840
b1 *
1"
#1850
0"
#1860
b10 *
1"
#1870
0"
#1880
b11 *
1"
#1890
0"
#1900
b100 *
1"
#1910
0"
#1920
b1001 '
b0 *
1"
#1930
0"
#1940
b1 *
1"
#1950
0"
#1960
b10 *
1"
#1970
0"
#1980
b11 *
1"
#1990
0"
#2000
b100 *
1"
#2010
0"
#2020
b0 *
b0 '
b10 (
1"
#2030
0"
#2040
1!
b1 *
1"
#2050
0"
#2060
b10 *
1"
#2070
0"
#2080
b11 *
1"
#2090
0"
#2100
b100 *
1"
#2110
0"
#2120
b1 '
b0 *
1"
#2130
0"
#2140
b1 *
1"
#2150
0"
#2160
b10 *
1"
#2170
0"
#2180
b11 *
1"
#2190
0"
#2200
b100 *
1"
#2210
0"
#2220
b0 *
b10 '
1"
#2230
0"
#2240
b1 *
1"
#2250
0"
#2260
b10 *
1"
#2270
0"
#2280
b11 *
1"
#2290
0"
#2300
b100 *
1"
#2310
0"
#2320
b11 '
b0 *
1"
#2330
0"
#2340
b1 *
0!
1"
#2350
0"
#2360
b10 *
1"
#2370
0"
#2380
b11 *
1"
#2390
0"
#2400
b100 *
1"
#2410
0"
#2420
b0 *
b100 '
1"
#2430
0"
#2440
b1 *
1"
#2450
0"
#2460
b10 *
1"
#2470
0"
#2480
b11 *
1"
#2490
0"
#2500
b100 *
1"
#2510
0"
#2520
b101 '
b0 *
1"
#2530
0"
#2540
b1 *
1"
#2550
0"
#2560
b10 *
1"
#2570
0"
#2580
b11 *
1"
#2590
0"
#2600
b100 *
1"
#2610
0"
#2620
b0 *
b110 '
1"
#2630
0"
#2640
b1 *
1"
#2650
0"
#2660
b10 *
1"
#2670
0"
#2680
b11 *
1"
#2690
0"
#2700
b100 *
1"
#2710
0"
#2720
b111 '
b0 *
1"
#2730
0"
#2740
b1 *
1"
#2750
0"
#2760
b10 *
1"
#2770
0"
#2780
b11 *
1"
#2790
0"
#2800
b100 *
1"
#2810
0"
#2820
b0 *
b1000 '
1"
#2830
0"
#2840
b1 *
1"
#2850
0"
#2860
b10 *
1"
#2870
0"
#2880
b11 *
1"
#2890
0"
#2900
b100 *
1"
#2910
0"
#2920
b1001 '
b0 *
1"
#2930
0"
#2940
b1 *
1"
#2950
0"
#2960
b10 *
1"
#2970
0"
#2980
b11 *
1"
#2990
0"
#3000
b100 *
1"
#3010
0"
#3020
b0 *
b0 '
b11 (
1"
#3030
0"
#3040
1!
b1 *
1"
#3050
0"
#3060
b10 *
1"
#3070
0"
#3080
b11 *
1"
#3090
0"
#3100
b100 *
1"
#3110
0"
#3120
b1 '
b0 *
1"
#3130
0"
#3140
b1 *
1"
#3150
0"
#3160
b10 *
1"
#3170
0"
#3180
b11 *
1"
#3190
0"
#3200
b100 *
1"
#3210
0"
#3220
b0 *
b10 '
1"
#3230
0"
#3240
b1 *
1"
#3250
0"
#3260
b10 *
1"
#3270
0"
#3280
b11 *
1"
#3290
0"
#3300
b100 *
1"
#3310
0"
#3320
b11 '
b0 *
1"
#3330
0"
#3340
b1 *
1"
#3350
0"
#3360
b10 *
1"
#3370
0"
#3380
b11 *
1"
#3390
0"
#3400
b100 *
1"
#3410
0"
#3420
b0 *
b100 '
1"
#3430
0"
#3440
0!
b1 *
1"
#3450
0"
#3460
b10 *
1"
#3470
0"
#3480
b11 *
1"
#3490
0"
#3500
b100 *
1"
#3510
0"
#3520
b101 '
b0 *
1"
#3530
0"
#3540
b1 *
1"
#3550
0"
#3560
b10 *
1"
#3570
0"
#3580
b11 *
1"
#3590
0"
#3600
b100 *
1"
#3610
0"
#3620
b0 *
b110 '
1"
#3630
0"
#3640
b1 *
1"
#3650
0"
#3660
b10 *
1"
#3670
0"
#3680
b11 *
1"
#3690
0"
#3700
b100 *
1"
#3710
0"
#3720
b111 '
b0 *
1"
#3730
0"
#3740
b1 *
1"
#3750
0"
#3760
b10 *
1"
#3770
0"
#3780
b11 *
1"
#3790
0"
#3800
b100 *
1"
#3810
0"
#3820
b0 *
b1000 '
1"
#3830
0"
#3840
b1 *
1"
#3850
0"
#3860
b10 *
1"
#3870
0"
#3880
b11 *
1"
#3890
0"
#3900
b100 *
1"
#3910
0"
#3920
b1001 '
b0 *
1"
#3930
0"
#3940
b1 *
1"
#3950
0"
#3960
b10 *
1"
#3970
0"
#3980
b11 *
1"
#3990
0"
#4000
b100 *
1"
#4010
0"
#4020
b0 *
b0 '
b100 (
1"
#4030
0"
#4040
1!
b1 *
1"
#4050
0"
#4060
b10 *
1"
#4070
0"
#4080
b11 *
1"
#4090
0"
#4100
b100 *
1"
#4110
0"
#4120
b1 '
b0 *
1"
#4130
0"
#4140
b1 *
1"
#4150
0"
#4160
b10 *
1"
#4170
0"
#4180
b11 *
1"
#4190
0"
#4200
b100 *
1"
#4210
0"
#4220
b0 *
b10 '
1"
#4230
0"
#4240
b1 *
1"
#4250
0"
#4260
b10 *
1"
#4270
0"
#4280
b11 *
1"
#4290
0"
#4300
b100 *
1"
#4310
0"
#4320
b11 '
b0 *
1"
#4330
0"
#4340
b1 *
1"
#4350
0"
#4360
b10 *
1"
#4370
0"
#4380
b11 *
1"
#4390
0"
#4400
b100 *
1"
#4410
0"
#4420
b0 *
b100 '
1"
#4430
0"
#4440
b1 *
1"
#4450
0"
#4460
b10 *
1"
#4470
0"
#4480
b11 *
1"
#4490
0"
#4500
b100 *
1"
#4510
0"
#4520
b101 '
b0 *
1"
#4530
0"
#4540
b1 *
0!
1"
#4550
0"
#4560
b10 *
1"
#4570
0"
#4580
b11 *
1"
#4590
0"
#4600
b100 *
1"
#4610
0"
#4620
b0 *
b110 '
1"
#4630
0"
#4640
b1 *
1"
#4650
0"
#4660
b10 *
1"
#4670
0"
#4680
b11 *
1"
#4690
0"
#4700
b100 *
1"
#4710
0"
#4720
b111 '
b0 *
1"
#4730
0"
#4740
b1 *
1"
#4750
0"
#4760
b10 *
1"
#4770
0"
#4780
b11 *
1"
#4790
0"
#4800
b100 *
1"
#4810
0"
#4820
b0 *
b1000 '
1"
#4830
0"
#4840
b1 *
1"
#4850
0"
#4860
b10 *
1"
#4870
0"
#4880
b11 *
1"
#4890
0"
#4900
b100 *
1"
#4910
0"
#4920
b1001 '
b0 *
1"
#4930
0"
#4940
b1 *
1"
#4950
0"
#4960
b10 *
1"
#4970
0"
#4980
b11 *
1"
#4990
0"
#5000
b100 *
1"
#5010
0"
#5020
b0 *
b0 '
b101 (
1"
#5030
0"
#5040
1!
b1 *
1"
#5050
0"
#5060
b10 *
1"
#5070
0"
#5080
b11 *
1"
#5090
0"
#5100
b100 *
1"
#5110
0"
#5120
b1 '
b0 *
1"
#5130
0"
#5140
b1 *
1"
#5150
0"
#5160
b10 *
1"
#5170
0"
#5180
b11 *
1"
#5190
0"
#5200
b100 *
1"
#5210
0"
#5220
b0 *
b10 '
1"
#5230
0"
#5240
b1 *
1"
#5250
0"
#5260
b10 *
1"
#5270
0"
#5280
b11 *
1"
#5290
0"
#5300
b100 *
1"
#5310
0"
#5320
b11 '
b0 *
1"
#5330
0"
#5340
b1 *
1"
#5350
0"
#5360
b10 *
1"
#5370
0"
#5380
b11 *
1"
#5390
0"
#5400
b100 *
1"
#5410
0"
#5420
b0 *
b100 '
1"
#5430
0"
#5440
b1 *
1"
#5450
0"
#5460
b10 *
1"
#5470
0"
#5480
b11 *
1"
#5490
0"
#5500
b100 *
1"
#5510
0"
#5520
b101 '
b0 *
1"
#5530
0"
#5540
b1 *
1"
#5550
0"
#5560
b10 *
1"
#5570
0"
#5580
b11 *
1"
#5590
0"
#5600
b100 *
1"
#5610
0"
#5620
b0 *
b110 '
1"
#5630
0"
#5640
0!
b1 *
1"
#5650
0"
#5660
b10 *
1"
#5670
0"
#5680
b11 *
1"
#5690
0"
#5700
b100 *
1"
#5710
0"
#5720
b111 '
b0 *
1"
#5730
0"
#5740
b1 *
1"
#5750
0"
#5760
b10 *
1"
#5770
0"
#5780
b11 *
1"
#5790
0"
#5800
b100 *
1"
#5810
0"
#5820
b0 *
b1000 '
1"
#5830
0"
#5840
b1 *
1"
#5850
0"
#5860
b10 *
1"
#5870
0"
#5880
b11 *
1"
#5890
0"
#5900
b100 *
1"
#5910
0"
#5920
b1001 '
b0 *
1"
#5930
0"
#5940
b1 *
1"
#5950
0"
#5960
b10 *
1"
#5970
0"
#5980
b11 *
1"
#5990
0"
#6000
b100 *
1"
#6010
0"
#6020
b0 *
b0 '
b110 (
1"
#6030
0"
#6040
1!
b1 *
1"
#6050
0"
#6060
b10 *
1"
#6070
0"
#6080
b11 *
1"
#6090
0"
#6100
b100 *
1"
#6110
0"
#6120
b1 '
b0 *
1"
#6130
0"
#6140
b1 *
1"
#6150
0"
#6160
b10 *
1"
#6170
0"
#6180
b11 *
1"
#6190
0"
#6200
b100 *
1"
#6210
0"
#6220
b0 *
b10 '
1"
#6230
0"
#6240
b1 *
1"
#6250
0"
#6260
b10 *
1"
#6270
0"
#6280
b11 *
1"
#6290
0"
#6300
b100 *
1"
#6310
0"
#6320
b11 '
b0 *
1"
#6330
0"
#6340
b1 *
1"
#6350
0"
#6360
b10 *
1"
#6370
0"
#6380
b11 *
1"
#6390
0"
#6400
b100 *
1"
#6410
0"
#6420
b0 *
b100 '
1"
#6430
0"
#6440
b1 *
1"
#6450
0"
#6460
b10 *
1"
#6470
0"
#6480
b11 *
1"
#6490
0"
#6500
b100 *
1"
#6510
0"
#6520
b101 '
b0 *
1"
#6530
0"
#6540
b1 *
1"
#6550
0"
#6560
b10 *
1"
#6570
0"
#6580
b11 *
1"
#6590
0"
#6600
b100 *
1"
#6610
0"
#6620
b0 *
b110 '
1"
#6630
0"
#6640
b1 *
1"
#6650
0"
#6660
b10 *
1"
#6670
0"
#6680
b11 *
1"
#6690
0"
#6700
b100 *
1"
#6710
0"
#6720
b111 '
b0 *
1"
#6730
0"
#6740
b1 *
0!
1"
#6750
0"
#6760
b10 *
1"
#6770
0"
#6780
b11 *
1"
#6790
0"
#6800
b100 *
1"
#6810
0"
#6820
b0 *
b1000 '
1"
#6830
0"
#6840
b1 *
1"
#6850
0"
#6860
b10 *
1"
#6870
0"
#6880
b11 *
1"
#6890
0"
#6900
b100 *
1"
#6910
0"
#6920
b1001 '
b0 *
1"
#6930
0"
#6940
b1 *
1"
#6950
0"
#6960
b10 *
1"
#6970
0"
#6980
b11 *
1"
#6990
0"
#7000
b100 *
1"
#7010
0"
#7020
b0 *
b0 '
b111 (
1"
#7030
0"
#7040
1!
b1 *
1"
#7050
0"
#7060
b10 *
1"
#7070
0"
#7080
b11 *
1"
#7090
0"
#7100
b100 *
1"
#7110
0"
#7120
b1 '
b0 *
1"
#7130
0"
#7140
b1 *
1"
#7150
0"
#7160
b10 *
1"
#7170
0"
#7180
b11 *
1"
#7190
0"
#7200
b100 *
1"
#7210
0"
#7220
b0 *
b10 '
1"
#7230
0"
#7240
b1 *
1"
#7250
0"
#7260
b10 *
1"
#7270
0"
#7280
b11 *
1"
#7290
0"
#7300
b100 *
1"
#7310
0"
#7320
b11 '
b0 *
1"
#7330
0"
#7340
b1 *
1"
#7350
0"
#7360
b10 *
1"
#7370
0"
#7380
b11 *
1"
#7390
0"
#7400
b100 *
1"
#7410
0"
#7420
b0 *
b100 '
1"
#7430
0"
#7440
b1 *
1"
#7450
0"
#7460
b10 *
1"
#7470
0"
#7480
b11 *
1"
#7490
0"
#7500
b100 *
1"
#7510
0"
#7520
b101 '
b0 *
1"
#7530
0"
#7540
b1 *
1"
#7550
0"
#7560
b10 *
1"
#7570
0"
#7580
b11 *
1"
#7590
0"
#7600
b100 *
1"
#7610
0"
#7620
b0 *
b110 '
1"
#7630
0"
#7640
b1 *
1"
#7650
0"
#7660
b10 *
1"
#7670
0"
#7680
b11 *
1"
#7690
0"
#7700
b100 *
1"
#7710
0"
#7720
b111 '
b0 *
1"
#7730
0"
#7740
b1 *
1"
#7750
0"
#7760
b10 *
1"
#7770
0"
#7780
b11 *
1"
#7790
0"
#7800
b100 *
1"
#7810
0"
#7820
b0 *
b1000 '
1"
#7830
0"
#7840
0!
b1 *
1"
#7850
0"
#7860
b10 *
1"
#7870
0"
#7880
b11 *
1"
#7890
0"
#7900
b100 *
1"
#7910
0"
#7920
b1001 '
b0 *
1"
#7930
0"
#7940
b1 *
1"
#7950
0"
#7960
b10 *
1"
#7970
0"
#7980
b11 *
1"
#7990
0"
#8000
b100 *
1"
#8010
0"
#8020
b0 *
b0 '
b1000 (
1"
#8030
0"
#8040
1!
b1 *
1"
#8050
0"
#8060
b10 *
1"
#8070
0"
#8080
b11 *
1"
#8090
0"
#8100
b100 *
1"
#8110
0"
#8120
b1 '
b0 *
1"
#8130
0"
#8140
b1 *
1"
#8150
0"
#8160
b10 *
1"
#8170
0"
#8180
b11 *
1"
#8190
0"
#8200
b100 *
1"
#8210
0"
#8220
b0 *
b10 '
1"
#8230
0"
#8240
b1 *
1"
#8250
0"
#8260
b10 *
1"
#8270
0"
#8280
b11 *
1"
#8290
0"
#8300
b100 *
1"
#8310
0"
#8320
b11 '
b0 *
1"
#8330
0"
#8340
b1 *
1"
#8350
0"
#8360
b10 *
1"
#8370
0"
#8380
b11 *
1"
#8390
0"
#8400
b100 *
1"
#8410
0"
#8420
b0 *
b100 '
1"
#8430
0"
#8440
b1 *
1"
#8450
0"
#8460
b10 *
1"
#8470
0"
#8480
b11 *
1"
#8490
0"
#8500
b100 *
1"
#8510
0"
#8520
b101 '
b0 *
1"
#8530
0"
#8540
b1 *
1"
#8550
0"
#8560
b10 *
1"
#8570
0"
#8580
b11 *
1"
#8590
0"
#8600
b100 *
1"
#8610
0"
#8620
b0 *
b110 '
1"
#8630
0"
#8640
b1 *
1"
#8650
0"
#8660
b10 *
1"
#8670
0"
#8680
b11 *
1"
#8690
0"
#8700
b100 *
1"
#8710
0"
#8720
b111 '
b0 *
1"
#8730
0"
#8740
b1 *
1"
#8750
0"
#8760
b10 *
1"
#8770
0"
#8780
b11 *
1"
#8790
0"
#8800
b100 *
1"
#8810
0"
#8820
b0 *
b1000 '
1"
#8830
0"
#8840
b1 *
1"
#8850
0"
#8860
b10 *
1"
#8870
0"
#8880
b11 *
1"
#8890
0"
#8900
b100 *
1"
#8910
0"
#8920
b1001 '
b0 *
1"
#8930
0"
#8940
b1 *
0!
1"
#8950
0"
#8960
b10 *
1"
#8970
0"
#8980
b11 *
1"
#8990
0"
#9000
b100 *
1"
#9010
0"
#9020
b0 *
b0 '
b1001 (
1"
#9030
0"
#9040
1!
b1 *
1"
#9050
0"
#9060
b10 *
1"
#9070
0"
#9080
b11 *
1"
#9090
0"
#9100
b100 *
1"
#9110
0"
#9120
b1 '
b0 *
1"
#9130
0"
#9140
b1 *
1"
#9150
0"
#9160
b10 *
1"
#9170
0"
#9180
b11 *
1"
#9190
0"
#9200
b100 *
1"
#9210
0"
#9220
b0 *
b10 '
1"
#9230
0"
#9240
b1 *
1"
#9250
0"
#9260
b10 *
1"
#9270
0"
#9280
b11 *
1"
#9290
0"
#9300
b100 *
1"
#9310
0"
#9320
b11 '
b0 *
1"
#9330
0"
#9340
b1 *
1"
#9350
0"
#9360
b10 *
1"
#9370
0"
#9380
b11 *
1"
#9390
0"
#9400
b100 *
1"
#9410
0"
#9420
b0 *
b100 '
1"
#9430
0"
#9440
b1 *
1"
#9450
0"
#9460
b10 *
1"
#9470
0"
#9480
b11 *
1"
#9490
0"
#9500
b100 *
1"
#9510
0"
#9520
b101 '
b0 *
1"
#9530
0"
#9540
b1 *
1"
#9550
0"
#9560
b10 *
1"
#9570
0"
#9580
b11 *
1"
#9590
0"
#9600
b100 *
1"
#9610
0"
#9620
b0 *
b110 '
1"
#9630
0"
#9640
b1 *
1"
#9650
0"
#9660
b10 *
1"
#9670
0"
#9680
b11 *
1"
#9690
0"
#9700
b100 *
1"
#9710
0"
#9720
b111 '
b0 *
1"
#9730
0"
#9740
b1 *
1"
#9750
0"
#9760
b10 *
1"
#9770
0"
#9780
b11 *
1"
#9790
0"
#9800
b100 *
1"
#9810
0"
#9820
b0 *
b1000 '
1"
#9830
0"
#9840
b1 *
1"
#9850
0"
#9860
b10 *
1"
#9870
0"
#9880
b11 *
1"
#9890
0"
#9900
b100 *
1"
#9910
0"
#9920
b1001 '
b0 *
1"
#9930
0"
#9940
b1 *
1"
#9950
0"
#9960
b10 *
1"
#9970
0"
#9980
b11 *
1"
#9990
0"
#10000
b100 *
1"
#10010
0"
#10020
b0 *
b0 '
b0 (
1)
1"
#10030
0"
#10040
b1 *
1"
#10050
0"
#10060
b10 *
1"
#10070
0"
#10080
b11 *
1"
#10090
0"
#10100
b100 *
1"
#10110
0"
#10120
b1 '
b0 *
1"
#10130
0"
#10140
b1 *
1"
#10150
0"
#10160
b10 *
1"
#10170
0"
#10180
b11 *
1"
#10190
0"
#10200
b100 *
1"
#10210
0"
#10220
b0 *
b10 '
1"
#10230
0"
#10240
b1 *
1"
#10250
0"
#10260
b10 *
1"
#10270
0"
#10280
b11 *
1"
#10290
0"
#10300
b100 *
1"
#10310
0"
#10320
b11 '
b0 *
1"
#10330
0"
#10340
b1 *
1"
#10350
0"
#10360
b10 *
1"
#10370
0"
#10380
b11 *
1"
#10390
0"
#10400
b100 *
1"
#10410
0"
#10420
b0 *
b100 '
1"
#10430
0"
#10440
b1 *
1"
#10450
0"
#10460
b10 *
1"
#10470
0"
#10480
b11 *
1"
#10490
0"
#10500
b100 *
1"
#10510
0"
#10520
b101 '
b0 *
1"
#10530
0"
#10540
b1 *
1"
#10550
0"
#10560
b10 *
1"
#10570
0"
#10580
b11 *
1"
#10590
0"
#10600
b100 *
1"
#10610
0"
#10620
b0 *
b110 '
1"
#10630
0"
#10640
b1 *
1"
#10650
0"
#10660
b10 *
1"
#10670
0"
#10680
b11 *
1"
#10690
0"
#10700
b100 *
1"
#10710
0"
#10720
b111 '
b0 *
1"
#10730
0"
#10740
b1 *
1"
#10750
0"
#10760
b10 *
1"
#10770
0"
#10780
b11 *
1"
#10790
0"
#10800
b100 *
1"
#10810
0"
#10820
b0 *
b1000 '
1"
#10830
0"
#10840
b1 *
1"
#10850
0"
#10860
b10 *
1"
#10870
0"
#10880
b11 *
1"
#10890
0"
#10900
b100 *
1"
#10910
0"
#10920
b1001 '
b0 *
1"
#10930
0"
#10940
b1 *
1"
#10950
0"
#10960
b10 *
1"
#10970
0"
#10980
b11 *
1"
#10990
0"
#11000
b100 *
1"
#11010
0"
#11020
b0 *
b0 '
b1 (
1"
#11030
0"
#11040
0!
b1 *
1"
#11050
0"
#11060
b10 *
1"
#11070
0"
#11080
b11 *
1"
#11090
0"
#11100
b100 *
1"
#11110
0"
#11120
b1 '
b0 *
1"
#11130
0"
#11140
b1 *
1!
1"
#11150
0"
#11160
b10 *
1"
#11170
0"
#11180
b11 *
1"
#11190
0"
#11200
b100 *
1"
#11210
0"
#11220
b0 *
b10 '
1"
#11230
0"
#11240
b1 *
1"
#11250
0"
#11260
b10 *
1"
#11270
0"
#11280
b11 *
1"
#11290
0"
#11300
b100 *
1"
#11310
0"
#11320
b11 '
b0 *
1"
#11330
0"
#11340
b1 *
1"
#11350
0"
#11360
b10 *
1"
#11370
0"
#11380
b11 *
1"
#11390
0"
#11400
b100 *
1"
#11410
0"
#11420
b0 *
b100 '
1"
#11430
0"
#11440
b1 *
1"
#11450
0"
#11460
b10 *
1"
#11470
0"
#11480
b11 *
1"
#11490
0"
#11500
b100 *
1"
#11510
0"
#11520
b101 '
b0 *
1"
#11530
0"
#11540
b1 *
1"
#11550
0"
#11560
b10 *
1"
#11570
0"
#11580
b11 *
1"
#11590
0"
#11600
b100 *
1"
#11610
0"
#11620
b0 *
b110 '
1"
#11630
0"
#11640
b1 *
1"
#11650
0"
#11660
b10 *
1"
#11670
0"
#11680
b11 *
1"
#11690
0"
#11700
b100 *
1"
#11710
0"
#11720
b111 '
b0 *
1"
#11730
0"
#11740
b1 *
1"
#11750
0"
#11760
b10 *
1"
#11770
0"
#11780
b11 *
1"
#11790
0"
#11800
b100 *
1"
#11810
0"
#11820
b0 *
b1000 '
1"
#11830
0"
#11840
b1 *
1"
#11850
0"
#11860
b10 *
1"
#11870
0"
#11880
b11 *
1"
#11890
0"
#11900
b100 *
1"
#11910
0"
#11920
b1001 '
b0 *
1"
#11930
0"
#11940
b1 *
1"
#11950
0"
