语法练习/i2c/i2c_ctrl.v
module  i2c_ctrl#(
    parameter   DEVICE_ADDR     =   7'b1010_000     ,   //i2c设备地址
    parameter   SYS_CLK_FREQ    =   26'd50_000_000  ,   //输入系统时钟频率    50MHZ  t=20ns
    parameter   SCL_FREQ        =      18'd250_000      //i2c设备scl时钟频率 250kHZ  t=20*200 ns = 4us
)
(
    input   wire            sys_clk     ,   //输入系统时钟,50MHz                                                --
    input   wire            sys_rst_n   ,   //输入复位信号,低电平有效                                                  --                                          
    
    input   wire            wr_en       ,   //输入写使能信号
    input   wire            rd_en       ,   //输入读使能信号
    input   wire            i2c_start   ,   //输入i2c触发信号
    input   wire            addr_num    ,   //输入i2c字节地址字节数
    input   wire    [15:0]  byte_addr   ,   //输入i2c字节地址
    input   wire    [7:0]   i2c_write_data     ,   //输入i2c设备数据

    output  reg             i2c_clk     ,   //i2c驱动时钟
    output  reg             i2c_end     ,   //i2c一次读/写操作完成
    output  reg     [7:0]   i2c_read_data     ,   //输出i2c设备读取数据
    
    output  reg             i2c_scl     ,   //输出至i2c设备的串行时钟信号scl
    inout   wire            i2c_sda         //输出至i2c设备的串行数据信号sda
);

//  sys_clk 50MHz  50分频->   i2c_clk  1MHz 
//  i2c_clk  1MHz  4分频->    
//  同时  对 i2c_clk 进行四分频 得到 250kHZ i2c_scl 


// parameter define
parameter   CNT_CLK_MAX     =   (SYS_CLK_FREQ/SCL_FREQ)  >>3'd3; //i2c_clk半个周期时长！！ 22c_clk的1个周期时长为 sys_clk的10个周期  

parameter   CNT_START_MAX   =   8'd100; //cnt_start计数器计数最大值

parameter   IDLE            =   4'd00,  //初始状态
            START_1         =   4'd01,  //开始状态1
            SEND_DEVICE_ADDR     =   4'd02,  //设备地址写入状态 + 控制写
            ACK_1           =   4'd03,  //应答状态1
            SEND_B_ADDR_H   =   4'd04,  //字节地址高八位写入状态
            ACK_2           =   4'd05,  //应答状态2
            SEND_B_ADDR_L   =   4'd06,  //字节地址低八位写入状态
            ACK_3           =   4'd07,  //应答状态3
            WR_DATA         =   4'd08,  //写数据状态
            ACK_4           =   4'd09,  //应答状态4
            START_2         =   4'd10,  //开始状态2
            SEND_RD_ADDR  =   4'd11,  //设备地址写入状态 + 控制读
            ACK_5           =   4'd12,  //应答状态5
            READ_DATA         =   4'd13,  //读数据状态
            N_ACK           =   4'd14,  //非应答状态
            STOP            =   4'd15;  //结束状态


wire            i2c_sda_in          ;   //sda输入数据寄存
wire            sda_en              ;   //sda数据写入使能信号

// reg   define
reg     [7:0]   cnt_sys_clk         ;   //系统时钟计数器,控制生成clk_i2c时钟信号
reg     [3:0]   state           ;   //状态机状态
reg             cnt_i2c_clk_en  ;   //cnt_i2c_clk计数器使能信号
reg     [1:0]   cnt_i2c_clk     ;   //clk_i2c时钟计数器,控制生成cnt_bit信号
reg     [2:0]   cnt_bit         ;   //sda比特计数器

reg             ack             ;   //应答信号
reg             i2c_sda_out     ;   //sda输出数据缓存
reg     [7:0]   rd_data_reg     ;   //自i2c设备读出数据


    //cnt_sys_clk  i2c_clk ： 计数 sys——clk， 产生 i2c_clk
    always @(posedge sys_clk or negedge sys_rst_n) begin
        if(!sys_rst_n) begin
            cnt_sys_clk <= 7'b0;
            i2c_clk  <= 1'b1;
        end
        else if(cnt_sys_clk == CNT_CLK_MAX - 1'b1) begin
            cnt_sys_clk <= 7'b0;
            i2c_clk <= ~i2c_clk;
        end
        else begin
            cnt_sys_clk <= cnt_sys_clk + 1'b1;
            i2c_clk  <= i2c_clk;
        end        
    end

    //cnt_i2c_clk_en： 检测 i2c——start 信号，  i2c_clk上升沿采集到，置cnt_i2c_clk_en高
    always@(posedge i2c_clk or negedge sys_rst_n) begin
        if(sys_rst_n == 1'b0)  
            cnt_i2c_clk_en  <=  1'b0;
        else    if((state == STOP) && (cnt_bit == 3'd3) &&(cnt_i2c_clk == 2'd3))
            cnt_i2c_clk_en  <=  1'b0;
        else    if(i2c_start == 1'b1) 
            cnt_i2c_clk_en  <=  1'b1;
        else
            cnt_i2c_clk_en <= cnt_i2c_clk_en;
    end

    // cnt_i2c_clk:  i2c_clk时钟计数器,控制生成cnt_bit信号
    always@(posedge i2c_clk or negedge sys_rst_n) begin
        if(sys_rst_n == 1'b0)
            cnt_i2c_clk <=  2'd0;
        else    if(cnt_i2c_clk_en == 1'b1)
            cnt_i2c_clk <=  cnt_i2c_clk + 1'b1;
        else 
            cnt_i2c_clk <=   2'b0;
    end

    // cnt_bit:sda比特计数器 记录传输的bit数    周期之比 sda:i2c_clk:sys_clk= 4:1: 1/
    always@(posedge i2c_clk or negedge sys_rst_n)
        if(sys_rst_n == 1'b0)
            cnt_bit <=  3'd0;
        else    if((state == IDLE) || (state == START_1) || (state == START_2)         //跳入到新的状态时， 重新计数、计数值清零
                    || (state == ACK_1) || (state == ACK_2) || (state == ACK_3)
                    || (state == ACK_4) || (state == ACK_5) || (state == N_ACK))
            cnt_bit <=  3'd0;
        else    if((cnt_bit == 3'd7) && (cnt_i2c_clk == 2'd3))  //计数值溢出 及时清零
            cnt_bit <=  3'd0;
        else    if((cnt_i2c_clk == 2'd3) && (state != IDLE)) //非空闲状态开始计数
            cnt_bit <=  cnt_bit + 1'b1;   //取 cnt_bit 周期 为 cnt_i2c_clk 的四倍时钟周期
                                          //  计数 sda跳变数    计数i2c_clk基础时钟跳变数

    //状态跳转部分           用于指挥 i2c 的 SCL SDA  
    always @(posedge i2c_clk or negedge sys_rst_n) begin
        if(!sys_rst_n) begin
            state <= IDLE;
        end
        else begin 
            case (state) 
                IDLE:
                    if (i2c_start == 1'b1) begin
                        state <= START_1;
                    end
                    else begin
                        state <= state;
                    end
                START_1:
                    if (cnt_i2c_clk == 2'd3) begin
                        state <= SEND_DEVICE_ADDR;
                    end
                    else begin
                        state <= state;
                    end
                SEND_DEVICE_ADDR: //发送器件地址 得到设备相应
                    if (cnt_bit == 3'd7 && cnt_i2c_clk == 2'd3) begin
                        state <= ACK_1;
                    end
                    else begin
                            state   <=  state;
                    end
                ACK_1: //根据 addr_num 判断 之后跳转状态 是发送 1个byte地址还是 2个byte地址
                    if((cnt_i2c_clk == 2'd3) && (ack == 1'b0))  begin
                            if(addr_num == 1'b1)
                                state   <=  SEND_B_ADDR_H;
                            else
                                state   <=  SEND_B_ADDR_L;
                    end
                    else begin
                            state   <=  state;
                    end
                SEND_B_ADDR_H:
                    if ((cnt_bit == 3'd7) && (cnt_i2c_clk == 2'd3)) begin
                        state <= ACK_2;
                    end
                    else begin
                            state   <=  state;
                    end
                ACK_2:
                    if((cnt_i2c_clk == 3) && (ack == 1'b0)) begin
                        state   <=  SEND_B_ADDR_L;
                    end
                    else begin
                        state   <=  state;
                    end
                SEND_B_ADDR_L:
                    if ((cnt_bit == 3'd7) && (cnt_i2c_clk == 2'd3)) begin
                        state <= ACK_3;
                    end
                    else begin
                        state   <=  state;
                    end
                ACK_3:
                    if((cnt_i2c_clk == 3) && (ack == 1'b0)) begin
                        if (wr_en == 1'b1) begin
                            state <= WR_DATA;
                        end
                        else if (rd_en == 1'b1) begin
                            state <= START_2;
                        end
                        else begin
                            state <= STOP;
                        end
                    end
                    else begin
                        state   <=  state;
                    end
                WR_DATA:
                    if ((cnt_bit == 3'd7) && (cnt_i2c_clk == 2'd3)) begin
                        state <= ACK_4;
                    end
                    else begin
                        state <= state;
                    end
                ACK_4:
                    if((cnt_i2c_clk == 3) && (ack == 1'b0)) begin
                        state <= STOP;
                    end
                    else begin
                        state <= state;
                    end              
                START_2:
                    if (cnt_i2c_clk == 2'd3) begin
                        state <= SEND_RD_ADDR;
                    end
                    else begin
                        state <= state;
                    end
                SEND_RD_ADDR: 
                    if ((cnt_bit == 3'd7) && (cnt_i2c_clk==2'd3)) begin
                        state <= ACK_5;
                    end
                    else begin
                        state <= state;
                    end
                ACK_5:
                    if ((cnt_i2c_clk == 2'd3) && (ack == 1'b0)) begin
                        state <= READ_DATA;
                    end
                    else begin
                        state   <=  state;
                    end
                READ_DATA: 
                    if ((cnt_i2c_clk == 2'd3) && (cnt_bit == 3'd7)) begin
                        state   <= N_ACK;
                    end
                    else begin
                        state   <=  state;
                    end
                N_ACK:
                    if (cnt_i2c_clk == 2'd3) begin
                        state <= STOP;
                    end
                    else begin
                       state <= state; 
                    end
                STOP:
                    if((cnt_bit == 3'd3) &&(cnt_i2c_clk == 2'd3)) begin
                        state   <=  IDLE;
                    end
                    else begin
                        state   <=  state;
                    end
            endcase
        end
    end

    // i2c SCL 根据状态改变  //每个state维持四个 i2c_clk时钟周期
    always @(*) begin  
        case (state)
            IDLE: //空闲状态  i2c_scl 传输时钟停止
                i2c_scl <= 1'b1;
            START_1://开始状态
                if (cnt_i2c_clk == 2'd3 )  begin
                    i2c_scl <= 1'b0; 
                end
                else begin
                    i2c_scl <= 1'b1;
                end
            //中间的n多个状态，cnt_i2c_clk不断计数， i2c_clk持续打节拍，  进行数据传输
            SEND_DEVICE_ADDR,ACK_1,SEND_B_ADDR_H,ACK_2,SEND_B_ADDR_L,
            ACK_3,WR_DATA,ACK_4,START_2,SEND_RD_ADDR,ACK_5,READ_DATA,N_ACK:
            begin
                    // i2c_clk [10] [10] [10] [10] 
                    // i2c_scl [0]  [1]  [1]  [0]  scl在中间两拍为高
                if ((cnt_i2c_clk == 2'd1 ) || (cnt_i2c_clk == 2'd2)) 
                    begin //（这里由i2c_clk四分频得到i2c_scl
                        i2c_scl <= 1'b1;
                    end
                else 
                    begin
                        i2c_scl <= 1'b0;
                    end
            end
                
            STOP: //结束状态 保持 高电平
                if ((cnt_bit == 3'd0) && (cnt_i2c_clk == 2'd0)) begin
                    i2c_scl <= 1'b0;  //拉低一节拍操作确认 cnt_bit清零传输完成，然后立即拉高（可能这个操作方便debug观察波形图吧
                end
                else begin
                    i2c_scl <= 1'b1;
                end
            default :
                i2c_scl <= 1'b1;
        endcase
    end

    //SDA数据线根据状态改变
    always @( *) begin
        case (state)
            IDLE:
                begin
                i2c_sda_out <= 1'b1; 
                end
            START_1:
                begin //开始第一节拍先拉高 i2c_sda，然后拉低，确保sda有下降沿信号产生
                    if (cnt_i2c_clk == 2'b0) begin
                        i2c_sda_out <= 1'd1;
                    end
                    else begin
                        i2c_sda_out <= 1'd0;
                    end
                end
            SEND_DEVICE_ADDR: //这里iic起始，需要 写操作， 写入从机地址+1bit操作位
                if (cnt_bit <= 3'd6) begin   // 7:1为器件地址，最低位为读写操作位， 
                    i2c_sda_out <= DEVICE_ADDR[ 6 - cnt_bit];
                end
                else begin //最低 一位地址为 0 表示写操作
                    i2c_sda_out <= 1'b0;
                end
            ACK_1:
                i2c_sda_out <= 1'b1;
            SEND_B_ADDR_H:
                i2c_sda_out <= byte_addr[15 - cnt_bit];
            ACK_2:
                i2c_sda_out <= 1'b1;
            SEND_B_ADDR_L:
                i2c_sda_out <= byte_addr[ 7 -cnt_bit ];
            ACK_3:
                i2c_sda_out <= 1'b1;
            WR_DATA:
                i2c_sda_out <= i2c_write_data[ 7- cnt_bit ];
            ACK_4:
                i2c_sda_out <= 1'b1;
            START_2:
                begin
                    if (cnt_i2c_clk == 2'b1) begin
                            i2c_sda_out <= 1'd1;
                        end
                        else begin
                            i2c_sda_out <= 1'd1;
                        end
                end
            SEND_RD_ADDR:
                if (cnt_bit <= 3'd6) begin
                    i2c_sda_out<= DEVICE_ADDR[6-cnt_bit];
                end
                else begin //1 读操作 ； 0 写操作
                    i2c_sda_out <= 1'b1; 
                end
            ACK_5:
                i2c_sda_out <= 1'b1;
            READ_DATA:
                if (cnt_i2c_clk == 2'd2) begin
                    rd_data_reg[7-cnt_bit] <= i2c_sda_in;
                end
                else begin
                    rd_data_reg <= rd_data_reg;
                end
            N_ACK:  //不应答 
                i2c_sda_out <= 1'b1;
            STOP:  //结束信号 在SCL为高电平时 进行SDA的拉高操作
                if ( (cnt_bit == 3'd0) && (cnt_i2c_clk <2'd3) ) begin
                    i2c_sda_out <= 1'b0;
                end
                else begin//最后一个 cnt_i2c_clk计数时拉高SDA， 确保 sda在scl为低电平时拉高
                    i2c_sda_out <= 1'b1;
                end
            default:
                begin
                  rd_data_reg <= rd_data_reg;
                  i2c_sda_out <= 1'b1;
                end 
        endcase
    end

    // iic通信一次 写操作、读操作结束标志
    always @(posedge i2c_clk or negedge sys_rst_n) begin
        if(!sys_rst_n) begin
            i2c_end <= 1'b0;
         end
        else if( (state==STOP) && (cnt_bit==3'd3) && (cnt_i2c_clk == 2'd3)) begin
            i2c_end <= 1'b1;
         end
        else
            i2c_end <= 1'b0;
    end

    //ack： 应答信号 寄存器，从机应答时 SDA会被从机拉低
    always @(*) begin
        case  (state)
            IDLE,START_1,SEND_DEVICE_ADDR,SEND_B_ADDR_H,SEND_B_ADDR_L,
            WR_DATA,START_2,SEND_RD_ADDR,READ_DATA,N_ACK:
                begin
                    ack <=  1'b1;
                end
            ACK_1,ACK_2,ACK_3,ACK_4,ACK_5:
                begin
                    if(cnt_i2c_clk == 2'd0) 
                            ack <= i2c_sda_in;
                    else 
                            ack <= ack;
                end
                
            default: ack <= 1'b1;
        endcase
    end

// 三态门控制 i2c_sda 
    //sda_en ： 1：主机操作   0：从机操作 sda端口呈现高阻态
    //接收数据 的时候 写入数据失能  
    assign  sda_en = ((state == READ_DATA) || (state == ACK_1) || (state == ACK_2)
                    || (state == ACK_3) || (state == ACK_4) || (state == ACK_5))
                        ? 1'b0 : 1'b1;

    //sda_en =1 ; 主设备控制总线   
    //sda_en =0 ; 主设备释放总线      // 主机数据输出；  高阻态 顾名思义：电阻超级大，近似于断路，可以当做线路断开
    assign i2c_sda = ( sda_en == 1'b1 )?  i2c_sda_out  :   1'bz;

    //sda_en =0 ；sda_in 三态门高阻态时sda_en=0， 接收sda总线上的数据
    assign i2c_sda_in  = i2c_sda;

endmodule

语法练习/i2c/tb_i2c_ctrl.v
`include "i2c_ctrl.v"

`timescale  1ns / 1ns

module tb_i2c_ctrl;

// i2c_ctrl Parameters
parameter PERIOD                   = 20                    ; //20ns

parameter DEVICE_ADDR              = 7'b1010_000           ;
parameter SYS_CLK_FREQ             = 26'd50_000_000        ;
parameter SCL_FREQ                 = 18'd250_000           ;


// i2c_ctrl Inputs
reg   sys_clk                              = 1'b0 ;
reg   sys_rst_n                            = 1'b0 ;

reg   wr_en                                = 1'b0 ;
reg   rd_en                                = 1'b0 ;

reg   i2c_start                            = 1'b0 ;
reg   addr_num                             = 1'b0 ;
reg   [15:0]  byte_addr                    = 16'b01100110_11001010 ;
reg   [7:0]   i2c_write_data                = 8'b1100_0101 ;

// i2c_ctrl Outputs
wire  i2c_clk                              ;
wire  i2c_end                              ;
wire  [7:0]  i2c_read_data                 ;
wire  i2c_scl                              ;

// i2c_ctrl Bidirs
wire    tb_i2c_sda                               ;

//-----------------------------------------------------

//从机端向三态门信号线发送数据
reg            tb_i2c_sda_link_en                 =1'b0;
reg            i2c_sda_slave_data              =1'b0;
wire           tb_i2c_sda_in           = tb_i2c_sda;
assign   tb_i2c_sda = (tb_i2c_sda_link_en==1)? i2c_sda_slave_data :1'bz;

// initial begin
//     force tb_i2c_sda = 1'b0;
// end

 
initial begin
    addr_num <= 1'b0;
    wr_en    <= 1'b0;
    rd_en    <= 1'b0;
end
initial begin
    #(PERIOD*1) sys_rst_n  =  0;
    #(PERIOD*1) sys_rst_n  =  1;
    #(PERIOD*23);
    i2c_start  = 1'b1; #(1000);
    i2c_start  = 1'b0; 
    rd_en =1'b1;
end
 

 
i2c_ctrl tb_i2c_ctrl
// #(
//     .DEVICE_ADDR             ( 7'b1010_011                    ),
//     .SYS_CLK_FREQ            ( 26'd50_000_000                 ),
//     .SCL_FREQ                ( 18'd250_000                    )
// )
(
    .sys_clk                 ( sys_clk                ),
    .sys_rst_n               ( sys_rst_n              ),
    .wr_en                   ( wr_en                  ),
    .rd_en                   ( rd_en                  ),
    .i2c_start               ( i2c_start              ),
    .addr_num                ( addr_num               ),
    .byte_addr               ( byte_addr       [15:0] ),
    .i2c_write_data          ( i2c_write_data  [7:0]  ),

    .i2c_clk                 ( i2c_clk                ),
    .i2c_end                 ( i2c_end                ),
    .i2c_read_data           ( i2c_read_data   [7:0]  ),
    .i2c_scl                 ( i2c_scl                ),

    .i2c_sda                 ( tb_i2c_sda             )
);

 

//-----clock and reset init---------
initial begin
    forever #(PERIOD/2)  sys_clk=~sys_clk;
end

initial begin
    forever begin
        #100;
        if ($time >= 2000000)  $finish ;
        if (($time >= 37030)  && ($time <= 41030) ) 
            begin
            tb_i2c_sda_link_en  = 1'b1;
            end
        else begin
           tb_i2c_sda_link_en   = 1'b0; 
        end
    end
end

initial begin
    $dumpfile("i2c_ctrl.vcd");           //生成的vcd文件名称
    $dumpvars(0, tb_i2c_ctrl);    // tb模块名称 module 的名字
    $dumpvars(0, tb_i2c_sda,tb_i2c_sda_in,tb_i2c_sda_link_en);
end

 
endmodule

简单时序/i2c_driver/i2c_ctrl.vcd
$date
	Tue Apr 18 13:51:43 2023
$end
$version
	Icarus Verilog
$end
$timescale
	1ns
$end
$scope module tb_i2c_ctrl $end
$scope module tb_i2c_ctrl $end
$var wire 1 ! addr_num $end
$var wire 16 " byte_addr [15:0] $end
$var wire 1 # i2c_sda $end
$var wire 1 $ i2c_sda_in $end
$var wire 1 % i2c_start $end
$var wire 8 & i2c_write_data [7:0] $end
$var wire 1 ' rd_en $end
$var wire 1 ( sys_clk $end
$var wire 1 ) sys_rst_n $end
$var wire 1 * wr_en $end
$var wire 1 + sda_en $end
$var parameter 4 , ACK_1 $end
$var parameter 4 - ACK_2 $end
$var parameter 4 . ACK_3 $end
$var parameter 4 / ACK_4 $end
$var parameter 4 0 ACK_5 $end
$var parameter 26 1 CNT_CLK_MAX $end
$var parameter 8 2 CNT_START_MAX $end
$var parameter 7 3 DEVICE_ADDR $end
$var parameter 4 4 IDLE $end
$var parameter 4 5 N_ACK $end
$var parameter 4 6 READ_DATA $end
$var parameter 18 7 SCL_FREQ $end
$var parameter 4 8 SEND_B_ADDR_H $end
$var parameter 4 9 SEND_B_ADDR_L $end
$var parameter 4 : SEND_DEVICE_ADDR $end
$var parameter 4 ; SEND_RD_ADDR $end
$var parameter 4 < START_1 $end
$var parameter 4 = START_2 $end
$var parameter 4 > STOP $end
$var parameter 26 ? SYS_CLK_FREQ $end
$var parameter 4 @ WR_DATA $end
$var reg 1 A ack $end
$var reg 3 B cnt_bit [2:0] $end
$var reg 2 C cnt_i2c_clk [1:0] $end
$var reg 1 D cnt_i2c_clk_en $end
$var reg 8 E cnt_sys_clk [7:0] $end
$var reg 1 F i2c_clk $end
$var reg 1 G i2c_end $end
$var reg 8 H i2c_read_data [7:0] $end
$var reg 1 I i2c_scl $end
$var reg 1 J i2c_sda_out $end
$var reg 8 K rd_data_reg [7:0] $end
$var reg 4 L state [3:0] $end
$upscope $end
$upscope $end
$scope module tb_i2c_ctrl $end
$var reg 1 M i2c_sda_slave_data $end
$upscope $end
$scope module tb_i2c_ctrl $end
$var wire 1 # tb_i2c_sda $end
$upscope $end
$scope module tb_i2c_ctrl $end
$var wire 1 N tb_i2c_sda_in $end
$upscope $end
$scope module tb_i2c_ctrl $end
$var reg 1 O tb_i2c_sda_link_en $end
$upscope $end
$enddefinitions $end
$comment Show the parameter values. $end
$dumpall
b1000 @
b10111110101111000010000000 ?
b1111 >
b1010 =
b1 <
b1011 ;
b10 :
b110 9
b100 8
b111101000010010000 7
b1101 6
b1110 5
b0 4
b1010000 3
b1100100 2
b11001 1
b1100 0
b1001 /
b111 .
b101 -
b11 ,
$end
#0
$dumpvars
0O
xN
0M
bx L
bx K
1J
1I
bx H
0G
xF
bx E
xD
b0 C
bx B
1A
x+
0*
1)
1(
1'
b11000101 &
0%
x$
x#
b110011011001010 "
0!
$end
#10
0(
#20
1N
1$
1#
1+
b0 L
b0 B
0D
1F
b0 E
1(
0)
#30
0(
#40
1(
#50
0(
#60
1(
#70
0(
#80
b1 E
1(
1)
#90
0(
#100
b10 E
1(
1M
#110
0(
#120
b11 E
1(
#130
0(
#140
b100 E
1(
#150
0(
#160
b101 E
1(
#170
0(
#180
b110 E
1(
#190
0(
#200
b111 E
1(
#210
0(
#220
b1000 E
1(
#230
0(
#240
b1001 E
1(
#250
0(
#260
b1010 E
1(
#270
0(
#280
b1011 E
1(
#290
0(
#300
b1100 E
1(
#310
0(
#320
b1101 E
1(
#330
0(
#340
b1110 E
1(
#350
0(
#360
b1111 E
1(
#370
0(
#380
b10000 E
1(
#390
0(
#400
b10001 E
1(
#410
0(
#420
b10010 E
1(
#430
0(
#440
b10011 E
1(
#450
0(
#460
b10100 E
1(
#470
0(
#480
b10101 E
1(
#490
0(
#500
b10110 E
1(
#510
0(
#520
b10111 E
1(
#530
0(
#540
b11000 E
1(
#550
0(
#560
0F
b0 E
1(
#570
0(
#580
b1 E
1(
#590
0(
#600
b10 E
1(
#610
0(
#620
b11 E
1(
#630
0(
#640
b100 E
1(
#650
0(
#660
b101 E
1(
#670
0(
#680
b110 E
1(
#690
0(
#700
b111 E
1(
#710
0(
#720
b1000 E
1(
#730
0(
#740
b1001 E
1(
#750
0(
#760
b1010 E
1(
#770
0(
#780
b1011 E
1(
#790
0(
#800
b1100 E
1(
#810
0(
#820
b1101 E
1(
#830
0(
#840
b1110 E
1(
#850
0(
#860
b1111 E
1(
#870
0(
#880
b10000 E
1(
#890
0(
#900
b10001 E
1(
#910
0(
#920
b10010 E
1(
#930
0(
#940
b10011 E
1(
#950
0(
#960
b10100 E
1(
#970
0(
#980
b10101 E
1(
#990
0(
#1000
b10110 E
1(
#1010
0(
#1020
b10111 E
1(
#1030
0(
#1040
b11000 E
1(
#1050
0(
#1060
1F
b0 E
1(
#1070
0(
#1080
b1 E
1(
1%
#1090
0(
#1100
b10 E
1(
#1110
0(
#1120
b11 E
1(
#1130
0(
#1140
b100 E
1(
#1150
0(
#1160
b101 E
1(
#1170
0(
#1180
b110 E
1(
#1190
0(
#1200
b111 E
1(
#1210
0(
#1220
b1000 E
1(
#1230
0(
#1240
b1001 E
1(
#1250
0(
#1260
b1010 E
1(
#1270
0(
#1280
b1011 E
1(
#1290
0(
#1300
b1100 E
1(
#1310
0(
#1320
b1101 E
1(
#1330
0(
#1340
b1110 E
1(
#1350
0(
#1360
b1111 E
1(
#1370
0(
#1380
b10000 E
1(
#1390
0(
#1400
b10001 E
1(
#1410
0(
#1420
b10010 E
1(
#1430
0(
#1440
b10011 E
1(
#1450
0(
#1460
b10100 E
1(
#1470
0(
#1480
b10101 E
1(
#1490
0(
#1500
b10110 E
1(
#1510
0(
#1520
b10111 E
1(
#1530
0(
#1540
b11000 E
1(
#1550
0(
#1560
0F
b0 E
1(
#1570
0(
#1580
b1 E
1(
#1590
0(
#1600
b10 E
1(
#1610
0(
#1620
b11 E
1(
#1630
0(
#1640
b100 E
1(
#1650
0(
#1660
b101 E
1(
#1670
0(
#1680
b110 E
1(
#1690
0(
#1700
b111 E
1(
#1710
0(
#1720
b1000 E
1(
#1730
0(
#1740
b1001 E
1(
#1750
0(
#1760
b1010 E
1(
#1770
0(
#1780
b1011 E
1(
#1790
0(
#1800
b1100 E
1(
#1810
0(
#1820
b1101 E
1(
#1830
0(
#1840
b1110 E
1(
#1850
0(
#1860
b1111 E
1(
#1870
0(
#1880
b10000 E
1(
#1890
0(
#1900
b10001 E
1(
#1910
0(
#1920
b10010 E
1(
#1930
0(
#1940
b10011 E
1(
#1950
0(
#1960
b10100 E
1(
#1970
0(
#1980
b10101 E
1(
#1990
0(
#2000
b10110 E
1(
#2010
0(
#2020
b10111 E
1(
#2030
0(
#2040
b11000 E
1(
#2050
0(
#2060
1D
b1 L
1F
b0 E
1(
#2070
0(
#2080
b1 E
1(
0%
#2090
0(
#2100
b10 E
1(
#2110
0(
#2120
b11 E
1(
#2130
0(
#2140
b100 E
1(
#2150
0(
#2160
b101 E
1(
#2170
0(
#2180
b110 E
1(
#2190
0(
#2200
b111 E
1(
#2210
0(
#2220
b1000 E
1(
#2230
0(
#2240
b1001 E
1(
#2250
0(
#2260
b1010 E
1(
#2270
0(
#2280
b1011 E
1(
#2290
0(
#2300
b1100 E
1(
#2310
0(
#2320
b1101 E
1(
#2330
0(
#2340
b1110 E
1(
#2350
0(
#2360
b1111 E
1(
#2370
0(
#2380
b10000 E
1(
#2390
0(
#2400
b10001 E
1(
#2410
0(
#2420
b10010 E
1(
#2430
0(
#2440
b10011 E
1(
#2450
0(
#2460
b10100 E
1(
#2470
0(
#2480
b10101 E
1(
#2490
0(
#2500
b10110 E
1(
#2510
0(
#2520
b10111 E
1(
#2530
0(
#2540
b11000 E
1(
#2550
0(
#2560
0F
b0 E
1(
#2570
0(
#2580
b1 E
1(
#2590
0(
#2600
b10 E
1(
#2610
0(
#2620
b11 E
1(
#2630
0(
#2640
b100 E
1(
#2650
0(
#2660
b101 E
1(
#2670
0(
#2680
b110 E
1(
#2690
0(
#2700
b111 E
1(
#2710
0(
#2720
b1000 E
1(
#2730
0(
#2740
b1001 E
1(
#2750
0(
#2760
b1010 E
1(
#2770
0(
#2780
b1011 E
1(
#2790
0(
#2800
b1100 E
1(
#2810
0(
#2820
b1101 E
1(
#2830
0(
#2840
b1110 E
1(
#2850
0(
#2860
b1111 E
1(
#2870
0(
#2880
b10000 E
1(
#2890
0(
#2900
b10001 E
1(
#2910
0(
#2920
b10010 E
1(
#2930
0(
#2940
b10011 E
1(
#2950
0(
#2960
b10100 E
1(
#2970
0(
#2980
b10101 E
1(
#2990
0(
#3000
b10110 E
1(
#3010
0(
#3020
b10111 E
1(
#3030
0(
#3040
b11000 E
1(
#3050
0(
#3060
0N
0$
0#
0J
b1 C
1F
b0 E
1(
#3070
0(
#3080
b1 E
1(
#3090
0(
#3100
b10 E
1(
#3110
0(
#3120
b11 E
1(
#3130
0(
#3140
b100 E
1(
#3150
0(
#3160
b101 E
1(
#3170
0(
#3180
b110 E
1(
#3190
0(
#3200
b111 E
1(
#3210
0(
#3220
b1000 E
1(
#3230
0(
#3240
b1001 E
1(
#3250
0(
#3260
b1010 E
1(
#3270
0(
#3280
b1011 E
1(
#3290
0(
#3300
b1100 E
1(
#3310
0(
#3320
b1101 E
1(
#3330
0(
#3340
b1110 E
1(
#3350
0(
#3360
b1111 E
1(
#3370
0(
#3380
b10000 E
1(
#3390
0(
#3400
b10001 E
1(
#3410
0(
#3420
b10010 E
1(
#3430
0(
#3440
b10011 E
1(
#3450
0(
#3460
b10100 E
1(
#3470
0(
#3480
b10101 E
1(
#3490
0(
#3500
b10110 E
1(
#3510
0(
#3520
b10111 E
1(
#3530
0(
#3540
b11000 E
1(
#3550
0(
#3560
0F
b0 E
1(
#3570
0(
#3580
b1 E
1(
#3590
0(
#3600
b10 E
1(
#3610
0(
#3620
b11 E
1(
#3630
0(
#3640
b100 E
1(
#3650
0(
#3660
b101 E
1(
#3670
0(
#3680
b110 E
1(
#3690
0(
#3700
b111 E
1(
#3710
0(
#3720
b1000 E
1(
#3730
0(
#3740
b1001 E
1(
#3750
0(
#3760
b1010 E
1(
#3770
0(
#3780
b1011 E
1(
#3790
0(
#3800
b1100 E
1(
#3810
0(
#3820
b1101 E
1(
#3830
0(
#3840
b1110 E
1(
#3850
0(
#3860
b1111 E
1(
#3870
0(
#3880
b10000 E
1(
#3890
0(
#3900
b10001 E
1(
#3910
0(
#3920
b10010 E
1(
#3930
0(
#3940
b10011 E
1(
#3950
0(
#3960
b10100 E
1(
#3970
0(
#3980
b10101 E
1(
#3990
0(
#4000
b10110 E
1(
#4010
0(
#4020
b10111 E
1(
#4030
0(
#4040
b11000 E
1(
#4050
0(
#4060
b10 C
1F
b0 E
1(
#4070
0(
#4080
b1 E
1(
#4090
0(
#4100
b10 E
1(
#4110
0(
#4120
b11 E
1(
#4130
0(
#4140
b100 E
1(
#4150
0(
#4160
b101 E
1(
#4170
0(
#4180
b110 E
1(
#4190
0(
#4200
b111 E
1(
#4210
0(
#4220
b1000 E
1(
#4230
0(
#4240
b1001 E
1(
#4250
0(
#4260
b1010 E
1(
#4270
0(
#4280
b1011 E
1(
#4290
0(
#4300
b1100 E
1(
#4310
0(
#4320
b1101 E
1(
#4330
0(
#4340
b1110 E
1(
#4350
0(
#4360
b1111 E
1(
#4370
0(
#4380
b10000 E
1(
#4390
0(
#4400
b10001 E
1(
#4410
0(
#4420
b10010 E
1(
#4430
0(
#4440
b10011 E
1(
#4450
0(
#4460
b10100 E
1(
#4470
0(
#4480
b10101 E
1(
#4490
0(
#4500
b10110 E
1(
#4510
0(
#4520
b10111 E
1(
#4530
0(
#4540
b11000 E
1(
#4550
0(
#4560
0F
b0 E
1(
#4570
0(
#4580
b1 E
1(
#4590
0(
#4600
b10 E
1(
#4610
0(
#4620
b11 E
1(
#4630
0(
#4640
b100 E
1(
#4650
0(
#4660
b101 E
1(
#4670
0(
#4680
b110 E
1(
#4690
0(
#4700
b111 E
1(
#4710
0(
#4720
b1000 E
1(
#4730
0(
#4740
b1001 E
1(
#4750
0(
#4760
b1010 E
1(
#4770
0(
#4780
b1011 E
1(
#4790
0(
#4800
b1100 E
1(
#4810
0(
#4820
b1101 E
1(
#4830
0(
#4840
b1110 E
1(
#4850
0(
#4860
b1111 E
1(
#4870
0(
#4880
b10000 E
1(
#4890
0(
#4900
b10001 E
1(
#4910
0(
#4920
b10010 E
1(
#4930
0(
#4940
b10011 E
1(
#4950
0(
#4960
b10100 E
1(
#4970
0(
#4980
b10101 E
1(
#4990
0(
#5000
b10110 E
1(
#5010
0(
#5020
b10111 E
1(
#5030
0(
#5040
b11000 E
1(
#5050
0(
#5060
0I
b11 C
1F
b0 E
1(
#5070
0(
#5080
b1 E
1(
#5090
0(
#5100
b10 E
1(
