语法练习/i2c/i2c_ctrl.v
module  i2c_ctrl#(
    parameter   DEVICE_ADDR     =   7'b1010_000     ,   //i2c设备地址
    parameter   SYS_CLK_FREQ    =   26'd50_000_000  ,   //输入系统时钟频率    50MHZ  t=20ns
    parameter   SCL_FREQ        =      18'd250_000      //i2c设备scl时钟频率 250kHZ  t=20*200 ns = 4us
)
(
    input   wire            sys_clk     ,   //输入系统时钟,50MHz                                                --
    input   wire            sys_rst_n   ,   //输入复位信号,低电平有效                                                  --                                          
    
    input   wire            wr_en       ,   //输入写使能信号
    input   wire            rd_en       ,   //输入读使能信号
    input   wire            i2c_start   ,   //输入i2c触发信号
    input   wire            addr_num    ,   //输入i2c字节地址字节数
    input   wire    [15:0]  byte_addr   ,   //输入i2c字节地址
    input   wire    [7:0]   i2c_write_data     ,   //输入i2c设备数据

    output  reg             i2c_clk     ,   //i2c驱动时钟
    output  reg             i2c_end     ,   //i2c一次读/写操作完成
    output  reg     [7:0]   i2c_read_data     ,   //输出i2c设备读取数据
    
    output  reg             i2c_scl     ,   //输出至i2c设备的串行时钟信号scl
    inout   wire            i2c_sda         //输出至i2c设备的串行数据信号sda
);

//  sys_clk 50MHz  50分频->   i2c_clk  1MHz 
//  i2c_clk  1MHz  4分频->    
//  同时  对 i2c_clk 进行四分频 得到 250kHZ i2c_scl 


// parameter define
parameter   CNT_CLK_MAX     =   (SYS_CLK_FREQ/SCL_FREQ)  >>3'd3; //i2c_clk半个周期时长！！ 22c_clk的1个周期时长为 sys_clk的10个周期  

parameter   CNT_START_MAX   =   8'd100; //cnt_start计数器计数最大值

parameter   IDLE            =   4'd00,  //初始状态
            START_1         =   4'd01,  //开始状态1
            SEND_DEVICE_ADDR     =   4'd02,  //设备地址写入状态 + 控制写
            ACK_1           =   4'd03,  //应答状态1
            SEND_B_ADDR_H   =   4'd04,  //字节地址高八位写入状态
            ACK_2           =   4'd05,  //应答状态2
            SEND_B_ADDR_L   =   4'd06,  //字节地址低八位写入状态
            ACK_3           =   4'd07,  //应答状态3
            WR_DATA         =   4'd08,  //写数据状态
            ACK_4           =   4'd09,  //应答状态4
            START_2         =   4'd10,  //开始状态2
            SEND_RD_ADDR  =   4'd11,  //设备地址写入状态 + 控制读
            ACK_5           =   4'd12,  //应答状态5
            READ_DATA         =   4'd13,  //读数据状态
            N_ACK           =   4'd14,  //非应答状态
            STOP            =   4'd15;  //结束状态


wire            i2c_sda_in          ;   //sda输入数据寄存
wire            sda_en              ;   //sda数据写入使能信号

// reg   define
reg     [7:0]   cnt_sys_clk         ;   //系统时钟计数器,控制生成clk_i2c时钟信号
reg     [3:0]   state           ;   //状态机状态
reg             cnt_i2c_clk_en  ;   //cnt_i2c_clk计数器使能信号
reg     [1:0]   cnt_i2c_clk     ;   //clk_i2c时钟计数器,控制生成cnt_bit信号
reg     [2:0]   cnt_bit         ;   //sda比特计数器

reg             ack             ;   //应答信号
reg             i2c_sda_out     ;   //sda输出数据缓存
reg     [7:0]   rd_data_reg     ;   //自i2c设备读出数据


    //cnt_sys_clk  i2c_clk ： 计数 sys——clk， 产生 i2c_clk
    always @(posedge sys_clk or negedge sys_rst_n) begin
        if(!sys_rst_n) begin
            cnt_sys_clk <= 7'b0;
            i2c_clk  <= 1'b1;
        end
        else if(cnt_sys_clk == CNT_CLK_MAX - 1'b1) begin
            cnt_sys_clk <= 7'b0;
            i2c_clk <= ~i2c_clk;
        end
        else begin
            cnt_sys_clk <= cnt_sys_clk + 1'b1;
            i2c_clk  <= i2c_clk;
        end        
    end

    //cnt_i2c_clk_en： 检测 i2c——start 信号，  i2c_clk上升沿采集到，置cnt_i2c_clk_en高
    always@(posedge i2c_clk or negedge sys_rst_n) begin
        if(sys_rst_n == 1'b0)  
            cnt_i2c_clk_en  <=  1'b0;
        else    if((state == STOP) && (cnt_bit == 3'd3) &&(cnt_i2c_clk == 2'd3))
            cnt_i2c_clk_en  <=  1'b0;
        else    if(i2c_start == 1'b1) 
            cnt_i2c_clk_en  <=  1'b1;
        else
            cnt_i2c_clk_en <= cnt_i2c_clk_en;
    end

    // cnt_i2c_clk:  i2c_clk时钟计数器,控制生成cnt_bit信号
    always@(posedge i2c_clk or negedge sys_rst_n) begin
        if(sys_rst_n == 1'b0)
            cnt_i2c_clk <=  2'd0;
        else    if(cnt_i2c_clk_en == 1'b1)
            cnt_i2c_clk <=  cnt_i2c_clk + 1'b1;
        else 
            cnt_i2c_clk <=   2'b0;
    end

    // cnt_bit:sda比特计数器 记录传输的bit数    周期之比 sda:i2c_clk:sys_clk= 4:1: 1/
    always@(posedge i2c_clk or negedge sys_rst_n)
        if(sys_rst_n == 1'b0)
            cnt_bit <=  3'd0;
        else    if((state == IDLE) || (state == START_1) || (state == START_2)         //跳入到新的状态时， 重新计数、计数值清零
                    || (state == ACK_1) || (state == ACK_2) || (state == ACK_3)
                    || (state == ACK_4) || (state == ACK_5) || (state == N_ACK))
            cnt_bit <=  3'd0;
        else    if((cnt_bit == 3'd7) && (cnt_i2c_clk == 2'd3))  //计数值溢出 及时清零
            cnt_bit <=  3'd0;
        else    if((cnt_i2c_clk == 2'd3) && (state != IDLE)) //非空闲状态开始计数
            cnt_bit <=  cnt_bit + 1'b1;   //取 cnt_bit 周期 为 cnt_i2c_clk 的四倍时钟周期
                                          //  计数 sda跳变数    计数i2c_clk基础时钟跳变数

    //状态跳转部分           用于指挥 i2c 的 SCL SDA  
    always @(posedge i2c_clk or negedge sys_rst_n) begin
        if(!sys_rst_n) begin
            state <= IDLE;
        end
        else begin 
            case (state) 
                IDLE:
                    if (i2c_start == 1'b1) begin
                        state <= START_1;
                    end
                    else begin
                        state <= state;
                    end
                START_1:
                    if (cnt_i2c_clk == 2'd3) begin
                        state <= SEND_DEVICE_ADDR;
                    end
                    else begin
                        state <= state;
                    end
                SEND_DEVICE_ADDR: //发送器件地址 得到设备相应
                    if (cnt_bit == 3'd7 && cnt_i2c_clk == 2'd3) begin
                        state <= ACK_1;
                    end
                    else begin
                            state   <=  state;
                    end
                ACK_1: //根据 addr_num 判断 之后跳转状态 是发送 1个byte地址还是 2个byte地址
                    if((cnt_i2c_clk == 2'd3) && (ack == 1'b0))  begin
                            if(addr_num == 1'b1)
                                state   <=  SEND_B_ADDR_H;
                            else
                                state   <=  SEND_B_ADDR_L;
                    end
                    else begin
                            state   <=  state;
                    end
                SEND_B_ADDR_H:
                    if ((cnt_bit == 3'd7) && (cnt_i2c_clk == 2'd3)) begin
                        state <= ACK_2;
                    end
                    else begin
                            state   <=  state;
                    end
                ACK_2:
                    if((cnt_i2c_clk == 3) && (ack == 1'b0)) begin
                        state   <=  SEND_B_ADDR_L;
                    end
                    else begin
                        state   <=  state;
                    end
                SEND_B_ADDR_L:
                    if ((cnt_bit == 3'd7) && (cnt_i2c_clk == 2'd3)) begin
                        state <= ACK_3;
                    end
                    else begin
                        state   <=  state;
                    end
                ACK_3:
                    if((cnt_i2c_clk == 3) && (ack == 1'b0)) begin
                        if (wr_en == 1'b1) begin
                            state <= WR_DATA;
                        end
                        else if (rd_en == 1'b1) begin
                            state <= START_2;
                        end
                        else begin
                            state <= STOP;
                        end
                    end
                    else begin
                        state   <=  state;
                    end
                WR_DATA:
                    if ((cnt_bit == 3'd7) && (cnt_i2c_clk == 2'd3)) begin
                        state <= ACK_4;
                    end
                    else begin
                        state <= state;
                    end
                ACK_4:
                    if((cnt_i2c_clk == 3) && (ack == 1'b0)) begin
                        state <= STOP;
                    end
                    else begin
                        state <= state;
                    end              
                START_2:
                    if (cnt_i2c_clk == 2'd3) begin
                        state <= SEND_RD_ADDR;
                    end
                    else begin
                        state <= state;
                    end
                SEND_RD_ADDR: 
                    if ((cnt_bit == 3'd7) && (cnt_i2c_clk==2'd3)) begin
                        state <= ACK_5;
                    end
                    else begin
                        state <= state;
                    end
                ACK_5:
                    if ((cnt_i2c_clk == 2'd3) && (ack == 1'b0)) begin
                        state <= READ_DATA;
                    end
                    else begin
                        state   <=  state;
                    end
                READ_DATA: 
                    if ((cnt_i2c_clk == 2'd3) && (cnt_bit == 3'd7)) begin
                        state   <= N_ACK;
                    end
                    else begin
                        state   <=  state;
                    end
                N_ACK:
                    if (cnt_i2c_clk == 2'd3) begin
                        state <= STOP;
                    end
                    else begin
                       state <= state; 
                    end
                STOP:
                    if((cnt_bit == 3'd3) &&(cnt_i2c_clk == 2'd3)) begin
                        state   <=  IDLE;
                    end
                    else begin
                        state   <=  state;
                    end
            endcase
        end
    end

    // i2c SCL 根据状态改变  //每个state维持四个 i2c_clk时钟周期
    always @(*) begin  
        case (state)
            IDLE: //空闲状态  i2c_scl 传输时钟停止
                i2c_scl <= 1'b1;
            START_1://开始状态
                if (cnt_i2c_clk == 2'd3 )  begin
                    i2c_scl <= 1'b0; 
                end
                else begin
                    i2c_scl <= 1'b1;
                end
            //中间的n多个状态，cnt_i2c_clk不断计数， i2c_clk持续打节拍，  进行数据传输
            SEND_DEVICE_ADDR,ACK_1,SEND_B_ADDR_H,ACK_2,SEND_B_ADDR_L,
            ACK_3,WR_DATA,ACK_4,START_2,SEND_RD_ADDR,ACK_5,READ_DATA,N_ACK:
            begin
                    // i2c_clk [10] [10] [10] [10] 
                    // i2c_scl [0]  [1]  [1]  [0]  scl在中间两拍为高
                if ((cnt_i2c_clk == 2'd1 ) || (cnt_i2c_clk == 2'd2)) 
                    begin //（这里由i2c_clk四分频得到i2c_scl
                        i2c_scl <= 1'b1;
                    end
                else 
                    begin
                        i2c_scl <= 1'b0;
                    end
            end
                
            STOP: //结束状态 保持 高电平
                if ((cnt_bit == 3'd0) && (cnt_i2c_clk == 2'd0)) begin
                    i2c_scl <= 1'b0;  //拉低一节拍操作确认 cnt_bit清零传输完成，然后立即拉高（可能这个操作方便debug观察波形图吧
                end
                else begin
                    i2c_scl <= 1'b1;
                end
            default :
                i2c_scl <= 1'b1;
        endcase
    end

    //SDA数据线根据状态改变
    always @( *) begin
        case (state)
            IDLE:
                begin
                i2c_sda_out <= 1'b1; 
                end
            START_1:
                begin //开始第一节拍先拉高 i2c_sda，然后拉低，确保sda有下降沿信号产生
                    if (cnt_i2c_clk == 2'b0) begin
                        i2c_sda_out <= 1'd1;
                    end
                    else begin
                        i2c_sda_out <= 1'd0;
                    end
                end
            SEND_DEVICE_ADDR: //这里iic起始，需要 写操作， 写入从机地址+1bit操作位
                if (cnt_bit <= 3'd6) begin   // 7:1为器件地址，最低位为读写操作位， 
                    i2c_sda_out <= DEVICE_ADDR[ 6 - cnt_bit];
                end
                else begin //最低 一位地址为 0 表示写操作
                    i2c_sda_out <= 1'b0;
                end
            ACK_1:
                i2c_sda_out <= 1'b1;
            SEND_B_ADDR_H:
                i2c_sda_out <= byte_addr[15 - cnt_bit];
            ACK_2:
                i2c_sda_out <= 1'b1;
            SEND_B_ADDR_L:
                i2c_sda_out <= byte_addr[ 7 -cnt_bit ];
            ACK_3:
                i2c_sda_out <= 1'b1;
            WR_DATA:
                i2c_sda_out <= i2c_write_data[ 7- cnt_bit ];
            ACK_4:
                i2c_sda_out <= 1'b1;
            START_2:
                begin
                    if (cnt_i2c_clk == 2'b1) begin
                            i2c_sda_out <= 1'd1;
                        end
                        else begin
                            i2c_sda_out <= 1'd1;
                        end
                end
            SEND_RD_ADDR:
                if (cnt_bit <= 3'd6) begin
                    i2c_sda_out<= DEVICE_ADDR[6-cnt_bit];
                end
                else begin //1 读操作 ； 0 写操作
                    i2c_sda_out <= 1'b1; 
                end
            ACK_5:
                i2c_sda_out <= 1'b1;
            READ_DATA:
                if (cnt_i2c_clk == 2'd2) begin
                    rd_data_reg[7-cnt_bit] <= i2c_sda_in;
                end
                else begin
                    rd_data_reg <= rd_data_reg;
                end
            N_ACK:  //不应答 
                i2c_sda_out <= 1'b1;
            STOP:  //结束信号 在SCL为高电平时 进行SDA的拉高操作
                if ( (cnt_bit == 3'd0) && (cnt_i2c_clk <2'd3) ) begin
                    i2c_sda_out <= 1'b0;
                end
                else begin//最后一个 cnt_i2c_clk计数时拉高SDA， 确保 sda在scl为低电平时拉高
                    i2c_sda_out <= 1'b1;
                end
            default:
                begin
                  rd_data_reg <= rd_data_reg;
                  i2c_sda_out <= 1'b1;
                end 
        endcase
    end

    // iic通信一次 写操作、读操作结束标志
    always @(posedge i2c_clk or negedge sys_rst_n) begin
        if(!sys_rst_n) begin
            i2c_end <= 1'b0;
         end
        else if( (state==STOP) && (cnt_bit==3'd3) && (cnt_i2c_clk == 2'd3)) begin
            i2c_end <= 1'b1;
         end
        else
            i2c_end <= 1'b0;
    end

    //ack： 应答信号 寄存器，从机应答时 SDA会被从机拉低
    always @(*) begin
        case  (state)
            IDLE,START_1,SEND_DEVICE_ADDR,SEND_B_ADDR_H,SEND_B_ADDR_L,
            WR_DATA,START_2,SEND_RD_ADDR,READ_DATA,N_ACK:
                begin
                    ack <=  1'b1;
                end
            ACK_1,ACK_2,ACK_3,ACK_4,ACK_5:
                begin
                    if(cnt_i2c_clk == 2'd0) 
                            ack <= i2c_sda_in;
                    else 
                            ack <= ack;
                end
                
            default: ack <= 1'b1;
        endcase
    end

// 三态门控制 i2c_sda 
    //sda_en ： 1：主机操作   0：从机操作 sda端口呈现高阻态
    //接收数据 的时候 写入数据失能  
    assign  sda_en = ((state == READ_DATA) || (state == ACK_1) || (state == ACK_2)
                    || (state == ACK_3) || (state == ACK_4) || (state == ACK_5))
                        ? 1'b0 : 1'b1;

    //sda_en =1 ; 主设备控制总线   
    //sda_en =0 ; 主设备释放总线      // 主机数据输出；  高阻态 顾名思义：电阻超级大，近似于断路，可以当做线路断开
    assign i2c_sda = ( sda_en == 1'b1 )?  i2c_sda_out  :   1'bz;

    //sda_en =0 ；sda_in 三态门高阻态时sda_en=0， 接收sda总线上的数据
    assign i2c_sda_in  = i2c_sda;

endmodule

语法练习/i2c/tb_i2c_ctrl.v
`include "i2c_ctrl.v"

`timescale  1ns / 1ns

module tb_i2c_ctrl;

// i2c_ctrl Parameters
parameter PERIOD                   = 20                    ; //20ns

parameter DEVICE_ADDR              = 7'b1010_000           ;
parameter SYS_CLK_FREQ             = 26'd50_000_000        ;
parameter SCL_FREQ                 = 18'd250_000           ;


// i2c_ctrl Inputs
reg   sys_clk                              = 1'b0 ;
reg   sys_rst_n                            = 1'b0 ;

reg   wr_en                                = 1'b0 ;
reg   rd_en                                = 1'b0 ;

reg   i2c_start                            = 1'b0 ;
reg   addr_num                             = 1'b0 ;
reg   [15:0]  byte_addr                    = 16'b01100110_11001010 ;
reg   [7:0]   i2c_write_data                = 8'b1100_0101 ;

// i2c_ctrl Outputs
wire  i2c_clk                              ;
wire  i2c_end                              ;
wire  [7:0]  i2c_read_data                 ;
wire  i2c_scl                              ;

// i2c_ctrl Bidirs
wire    tb_i2c_sda                               ;

//-----------------------------------------------------

//从机端向三态门信号线发送数据
reg            tb_i2c_sda_link_en                 =1'b0;
reg            i2c_sda_slave_data              =1'b0;
wire           tb_i2c_sda_in           = tb_i2c_sda;
assign   tb_i2c_sda = (tb_i2c_sda_link_en==1)? i2c_sda_slave_data :1'bz;

// initial begin
//     force tb_i2c_sda = 1'b0;
// end

 
initial begin
    addr_num <= 1'b0;
    wr_en    <= 1'b0;
    rd_en    <= 1'b0;
end
initial begin
    #(PERIOD*1) sys_rst_n  =  0;
    #(PERIOD*1) sys_rst_n  =  1;
    #(PERIOD*23);
    i2c_start  = 1'b1; #(1000);
    i2c_start  = 1'b0; 
    rd_en =1'b1;
end
 

 
i2c_ctrl tb_i2c_ctrl
// #(
//     .DEVICE_ADDR             ( 7'b1010_011                    ),
//     .SYS_CLK_FREQ            ( 26'd50_000_000                 ),
//     .SCL_FREQ                ( 18'd250_000                    )
// )
(
    .sys_clk                 ( sys_clk                ),
    .sys_rst_n               ( sys_rst_n              ),
    .wr_en                   ( wr_en                  ),
    .rd_en                   ( rd_en                  ),
    .i2c_start               ( i2c_start              ),
    .addr_num                ( addr_num               ),
    .byte_addr               ( byte_addr       [15:0] ),
    .i2c_write_data          ( i2c_write_data  [7:0]  ),

    .i2c_clk                 ( i2c_clk                ),
    .i2c_end                 ( i2c_end                ),
    .i2c_read_data           ( i2c_read_data   [7:0]  ),
    .i2c_scl                 ( i2c_scl                ),

    .i2c_sda                 ( tb_i2c_sda             )
);

 

//-----clock and reset init---------
initial begin
    forever #(PERIOD/2)  sys_clk=~sys_clk;
end

initial begin
    forever begin
        #100;
        if ($time >= 2000000)  $finish ;
        if (($time >= 37030)  && ($time <= 41030) ) 
            begin
            tb_i2c_sda_link_en  = 1'b1;
            end
        else begin
           tb_i2c_sda_link_en   = 1'b0; 
        end
    end
end

initial begin
    $dumpfile("i2c_ctrl.vcd");           //生成的vcd文件名称
    $dumpvars(0, tb_i2c_ctrl);    // tb模块名称 module 的名字
    $dumpvars(0, tb_i2c_sda,tb_i2c_sda_in,tb_i2c_sda_link_en);
end

 
endmodule

语法练习/i2c/i2c_ctrl.vcd
$date
	Mon Apr 17 22:12:49 2023
$end
$version
	Icarus Verilog
$end
$timescale
	1ns
$end
$scope module tb_i2c_ctrl $end
$scope module tb_i2c_ctrl $end
$var wire 1 ! addr_num $end
$var wire 16 " byte_addr [15:0] $end
$var wire 1 # i2c_sda $end
$var wire 1 $ i2c_sda_in $end
$var wire 1 % i2c_start $end
$var wire 8 & i2c_write_data [7:0] $end
$var wire 1 ' rd_en $end
$var wire 1 ( sys_clk $end
$var wire 1 ) sys_rst_n $end
$var wire 1 * wr_en $end
$var wire 1 + sda_en $end
$var parameter 4 , ACK_1 $end
$var parameter 4 - ACK_2 $end
$var parameter 4 . ACK_3 $end
$var parameter 4 / ACK_4 $end
$var parameter 4 0 ACK_5 $end
$var parameter 26 1 CNT_CLK_MAX $end
$var parameter 8 2 CNT_START_MAX $end
$var parameter 7 3 DEVICE_ADDR $end
$var parameter 4 4 IDLE $end
$var parameter 4 5 N_ACK $end
$var parameter 4 6 READ_DATA $end
$var parameter 18 7 SCL_FREQ $end
$var parameter 4 8 SEND_B_ADDR_H $end
$var parameter 4 9 SEND_B_ADDR_L $end
$var parameter 4 : SEND_DEVICE_ADDR $end
$var parameter 4 ; SEND_RD_ADDR $end
$var parameter 4 < START_1 $end
$var parameter 4 = START_2 $end
$var parameter 4 > STOP $end
$var parameter 26 ? SYS_CLK_FREQ $end
$var parameter 4 @ WR_DATA $end
$var reg 1 A ack $end
$var reg 3 B cnt_bit [2:0] $end
$var reg 2 C cnt_i2c_clk [1:0] $end
$var reg 1 D cnt_i2c_clk_en $end
$var reg 8 E cnt_sys_clk [7:0] $end
$var reg 1 F i2c_clk $end
$var reg 1 G i2c_end $end
$var reg 8 H i2c_read_data [7:0] $end
$var reg 1 I i2c_scl $end
$var reg 1 J i2c_sda_out $end
$var reg 8 K rd_data_reg [7:0] $end
$var reg 4 L state [3:0] $end
$upscope $end
$upscope $end
$scope module tb_i2c_ctrl $end
$var wire 1 # tb_i2c_sda $end
$upscope $end
$scope module tb_i2c_ctrl $end
$var wire 1 M tb_i2c_sda_in $end
$upscope $end
$scope module tb_i2c_ctrl $end
$var reg 1 N tb_i2c_sda_link_en $end
$upscope $end
$enddefinitions $end
$comment Show the parameter values. $end
$dumpall
b1000 @
b10111110101111000010000000 ?
b1111 >
b1010 =
b1 <
b1011 ;
b10 :
b110 9
b100 8
b111101000010010000 7
b1101 6
b1110 5
b0 4
b1010000 3
b1100100 2
b11001 1
b1100 0
b1001 /
b111 .
b101 -
b11 ,
$end
#0
$dumpvars
0N
1M
b0 L
bx K
1J
1I
bx H
0G
1F
b0 E
0D
b0 C
b0 B
1A
1+
0*
0)
0(
0'
b11000101 &
0%
1$
1#
b110011011001010 "
0!
$end
#10
1(
#20
0(
#30
1(
#40
0(
1)
#50
b1 E
1(
#60
0(
#70
b10 E
1(
#80
0(
#90
b11 E
1(
#100
0(
#110
b100 E
1(
#120
0(
#130
b101 E
1(
#140
0(
#150
b110 E
1(
#160
0(
#170
b111 E
1(
#180
0(
#190
b1000 E
1(
#200
0(
#210
b1001 E
1(
#220
0(
#230
b1010 E
1(
#240
0(
#250
b1011 E
1(
#260
0(
#270
b1100 E
1(
#280
0(
#290
b1101 E
1(
#300
0(
#310
b1110 E
1(
#320
0(
#330
b1111 E
1(
#340
0(
#350
b10000 E
1(
#360
0(
#370
b10001 E
1(
#380
0(
#390
b10010 E
1(
#400
0(
#410
b10011 E
1(
#420
0(
#430
b10100 E
1(
#440
0(
#450
b10101 E
1(
#460
0(
#470
b10110 E
1(
#480
0(
#490
b10111 E
1(
#500
0(
1%
#510
b11000 E
1(
#520
0(
#530
0F
b0 E
1(
#540
0(
#550
b1 E
1(
#560
0(
#570
b10 E
1(
#580
0(
#590
b11 E
1(
#600
0(
#610
b100 E
1(
#620
0(
#630
b101 E
1(
#640
0(
#650
b110 E
1(
#660
0(
#670
b111 E
1(
#680
0(
#690
b1000 E
1(
#700
0(
#710
b1001 E
1(
#720
0(
#730
b1010 E
1(
#740
0(
#750
b1011 E
1(
#760
0(
#770
b1100 E
1(
#780
0(
#790
b1101 E
1(
#800
0(
#810
b1110 E
1(
#820
0(
#830
b1111 E
1(
#840
0(
#850
b10000 E
1(
#860
0(
#870
b10001 E
1(
#880
0(
#890
b10010 E
1(
#900
0(
#910
b10011 E
1(
#920
0(
#930
b10100 E
1(
#940
0(
#950
b10101 E
1(
#960
0(
#970
b10110 E
1(
#980
0(
#990
b10111 E
1(
#1000
0(
#1010
b11000 E
1(
#1020
0(
#1030
1D
b1 L
1F
b0 E
1(
#1040
0(
#1050
b1 E
1(
#1060
0(
#1070
b10 E
1(
#1080
0(
#1090
b11 E
1(
#1100
0(
#1110
b100 E
1(
#1120
0(
#1130
b101 E
1(
#1140
0(
#1150
b110 E
1(
#1160
0(
#1170
b111 E
1(
#1180
0(
#1190
b1000 E
1(
#1200
0(
#1210
b1001 E
1(
#1220
0(
#1230
b1010 E
1(
#1240
0(
#1250
b1011 E
1(
#1260
0(
#1270
b1100 E
1(
#1280
0(
#1290
b1101 E
1(
#1300
0(
#1310
b1110 E
1(
#1320
0(
#1330
b1111 E
1(
#1340
0(
#1350
b10000 E
1(
#1360
0(
#1370
b10001 E
1(
#1380
0(
#1390
b10010 E
1(
#1400
0(
#1410
b10011 E
1(
#1420
0(
#1430
b10100 E
1(
#1440
0(
#1450
b10101 E
1(
#1460
0(
#1470
b10110 E
1(
#1480
0(
#1490
b10111 E
1(
#1500
0(
1'
0%
#1510
b11000 E
1(
#1520
0(
#1530
0F
b0 E
1(
#1540
0(
#1550
b1 E
1(
#1560
0(
#1570
b10 E
1(
#1580
0(
#1590
b11 E
1(
#1600
0(
#1610
b100 E
1(
#1620
0(
#1630
b101 E
1(
#1640
0(
#1650
b110 E
1(
#1660
0(
#1670
b111 E
1(
#1680
0(
#1690
b1000 E
1(
#1700
0(
#1710
b1001 E
1(
#1720
0(
#1730
b1010 E
1(
#1740
0(
#1750
b1011 E
1(
#1760
0(
#1770
b1100 E
1(
#1780
0(
#1790
b1101 E
1(
#1800
0(
#1810
b1110 E
1(
#1820
0(
#1830
b1111 E
1(
#1840
0(
#1850
b10000 E
1(
#1860
0(
#1870
b10001 E
1(
#1880
0(
#1890
b10010 E
1(
#1900
0(
#1910
b10011 E
1(
#1920
0(
#1930
b10100 E
1(
#1940
0(
#1950
b10101 E
1(
#1960
0(
#1970
b10110 E
1(
#1980
0(
#1990
b10111 E
1(
#2000
0(
#2010
b11000 E
1(
#2020
0(
#2030
0M
0$
0#
0J
b1 C
1F
b0 E
1(
#2040
0(
#2050
b1 E
1(
#2060
0(
#2070
b10 E
1(
#2080
0(
#2090
b11 E
1(
#2100
0(
#2110
b100 E
1(
#2120
0(
#2130
b101 E
1(
#2140
0(
#2150
b110 E
1(
#2160
0(
#2170
b111 E
1(
#2180
0(
#2190
b1000 E
1(
#2200
0(
#2210
b1001 E
1(
#2220
0(
#2230
b1010 E
1(
#2240
0(
#2250
b1011 E
1(
#2260
0(
#2270
b1100 E
1(
#2280
0(
#2290
b1101 E
1(
#2300
0(
#2310
b1110 E
1(
#2320
0(
#2330
b1111 E
1(
#2340
0(
#2350
b10000 E
1(
#2360
0(
#2370
b10001 E
1(
#2380
0(
#2390
b10010 E
1(
#2400
0(
#2410
b10011 E
1(
#2420
0(
#2430
b10100 E
1(
#2440
0(
#2450
b10101 E
1(
#2460
0(
#2470
b10110 E
1(
#2480
0(
#2490
b10111 E
1(
#2500
0(
#2510
b11000 E
1(
#2520
0(
#2530
0F
b0 E
1(
#2540
0(
#2550
b1 E
1(
#2560
0(
#2570
b10 E
1(
#2580
0(
#2590
b11 E
1(
#2600
0(
#2610
b100 E
1(
#2620
0(
#2630
b101 E
1(
#2640
0(
#2650
b110 E
1(
#2660
0(
#2670
b111 E
1(
#2680
0(
#2690
b1000 E
1(
#2700
0(
#2710
b1001 E
1(
#2720
0(
#2730
b1010 E
1(
#2740
0(
#2750
b1011 E
1(
#2760
0(
#2770
b1100 E
1(
#2780
0(
#2790
b1101 E
1(
#2800
0(
#2810
b1110 E
1(
#2820
0(
#2830
b1111 E
1(
#2840
0(
#2850
b10000 E
1(
#2860
0(
#2870
b10001 E
1(
#2880
0(
#2890
b10010 E
1(
#2900
0(
#2910
b10011 E
1(
#2920
0(
#2930
b10100 E
1(
#2940
0(
#2950
b10101 E
1(
#2960
0(
#2970
b10110 E
1(
#2980
0(
#2990
b10111 E
1(
#3000
0(
#3010
b11000 E
1(
#3020
0(
#3030
b10 C
1F
b0 E
1(
#3040
0(
#3050
b1 E
1(
#3060
0(
#3070
b10 E
1(
#3080
0(
#3090
b11 E
1(
#3100
0(
#3110
b100 E
1(
#3120
0(
#3130
b101 E
1(
#3140
0(
#3150
b110 E
1(
#3160
0(
#3170
b111 E
1(
#3180
0(
#3190
b1000 E
1(
#3200
0(
#3210
b1001 E
1(
#3220
0(
#3230
b1010 E
1(
#3240
0(
#3250
b1011 E
1(
#3260
0(
#3270
b1100 E
1(
#3280
0(
#3290
b1101 E
1(
#3300
0(
#3310
b1110 E
1(
#3320
0(
#3330
b1111 E
1(
#3340
0(
#3350
b10000 E
1(
#3360
0(
#3370
b10001 E
1(
#3380
0(
#3390
b10010 E
1(
#3400
0(
#3410
b10011 E
1(
#3420
0(
#3430
b10100 E
1(
#3440
0(
#3450
b10101 E
1(
#3460
0(
#3470
b10110 E
1(
#3480
0(
#3490
b10111 E
1(
#3500
0(
#3510
b11000 E
1(
#3520
0(
#3530
0F
b0 E
1(
#3540
0(
#3550
b1 E
1(
#3560
0(
#3570
b10 E
1(
#3580
0(
#3590
b11 E
1(
#3600
0(
#3610
b100 E
1(
#3620
0(
#3630
b101 E
1(
#3640
0(
#3650
b110 E
1(
#3660
0(
#3670
b111 E
1(
#3680
0(
#3690
b1000 E
1(
#3700
0(
#3710
b1001 E
1(
#3720
0(
#3730
b1010 E
1(
#3740
0(
#3750
b1011 E
1(
#3760
0(
#3770
b1100 E
1(
#3780
0(
#3790
b1101 E
1(
#3800
0(
#3810
b1110 E
1(
#3820
0(
#3830
b1111 E
1(
#3840
0(
#3850
b10000 E
1(
#3860
0(
#3870
b10001 E
1(
#3880
0(
#3890
b10010 E
1(
#3900
0(
#3910
b10011 E
1(
#3920
0(
#3930
b10100 E
1(
#3940
0(
#3950
b10101 E
1(
#3960
0(
#3970
b10110 E
1(
#3980
0(
#3990
b10111 E
1(
#4000
0(
#4010
b11000 E
1(
#4020
0(
#4030
0I
b11 C
1F
b0 E
1(
#4040
0(
#4050
b1 E
1(
#4060
0(
#4070
b10 E
1(
#4080
0(
#4090
b11 E
1(
#4100
0(
#4110
b100 E
1(
#4120
0(
#4130
b101 E
1(
#4140
0(
#4150
b110 E
1(
#4160
0(
#4170
b111 E
1(
#4180
0(
#4190
b1000 E
1(
#4200
0(
#4210
b1001 E
1(
#4220
0(
#4230
b1010 E
1(
#4240
0(
#4250
b1011 E
1(
#4260
0(
#4270
b1100 E
1(
#4280
0(
#4290
b1101 E
1(
#4300
0(
#4310
b1110 E
1(
#4320
0(
#4330
b1111 E
1(
#4340
0(
#4350
b10000 E
1(
#4360
0(
#4370
b10001 E
1(
#4380
0(
#4390
b10010 E
1(
#4400
0(
#4410
b10011 E
1(
#4420
0(
#4430
b10100 E
1(
#4440
0(
#4450
b10101 E
1(
#4460
0(
#4470
b10110 E
1(
#4480
0(
#4490
b10111 E
1(
#4500
0(
#4510
b11000 E
1(
#4520
0(
#4530
0F
b0 E
1(
#4540
0(
#4550
b1 E
1(
#4560
0(
#4570
b10 E
1(
#4580
0(
#4590
b11 E
1(
#4600
0(
#4610
b100 E
1(
#4620
0(
#4630
b101 E
1(
#4640
0(
#4650
b110 E
1(
#4660
0(
#4670
b111 E
1(
#4680
0(
#4690
b1000 E
1(
#4700
0(
#4710
b1001 E
1(
#4720
0(
#4730
b1010 E
1(
#4740
0(
#4750
b1011 E
1(
#4760
0(
#4770
b1100 E
1(
#4780
0(
#4790
b1101 E
1(
#4800
0(
#4810
b1110 E
1(
#4820
0(
#4830
b1111 E
1(
#4840
0(
#4850
b10000 E
1(
#4860
0(
#4870
b10001 E
1(
#4880
0(
#4890
b10010 E
1(
#4900
0(
#4910
b10011 E
1(
#4920
0(
#4930
b10100 E
1(
#4940
0(
#4950
b10101 E
1(
#4960
0(
#4970
b10110 E
1(
#4980
0(
#4990
b10111 E
1(
#5000
0(
#5010
b11000 E
1(
#5020
0(
#5030
1M
1$
1#
1J
b0 C
b10 L
1F
b0 E
1(
#5040
0(
#5050
b1 E
1(
#5060
0(
#5070
b10 E
1(
#5080
0(
#5090
b11 E
1(
#5100
0(
#5110
b100 E
1(
#5120
0(
#5130
b101 E
1(
#5140
0(
#5150
b110 E
1(
#5160
0(
